{"title":"\u0111\u1ec1 thi n\u0103ng l\u1ef1c ti\u1ebfng Nh\u1eadt N3 \u0111\u1ec1 s\u1ed1\u00a087","url":"https:\/\/tuhoconline.net\/de-thi-nang-luc-tieng-nhat-n3-de-so-87.html","keywords":["\u0110\u1ec1 thi N3","Luy\u1ec7n thi N3"],"quizzes":[{"type":"choices","source_title":null,"url":null,"keywords":[],"pre_content":null,"content":"<p><strong><a aria-describedby=\"tt\" target=\"_blank\">\u6b21<\/a>\u306e<a aria-describedby=\"tt\" target=\"_blank\">\u6587<\/a>\u306e\uff3f\u2605\uff3f\u306b\u3082\u3063\u3068\u3082\u3088\u3044\u3082\u306e\u3092\u3001\uff11\u30fb\uff12\u30fb\uff13\u30fb\uff14\u304b\u3089<a aria-describedby=\"tt\" target=\"_blank\">\u4e00<\/a>\u3064\u3048\u3089\u3073\u306a\u3055\u3044<\/strong><\/p>\n<p>\u3044\u3044\uff3f\uff3f\u3000\uff3f\uff3f\u3000\uff3f\u2605\uff3f\u3000\uff3f\uff3f\u3001\u307b\u3081\u308b\u3053\u3068\u3082<a aria-describedby=\"tt\" target=\"_blank\">\u5fd8<\/a>\u308c\u306a\u3044\u3002<\/p>","choices":["<span><\/span> <label> <input type=\"radio\" name=\"question_349_4291\" value=\"1\"> \u53f1\u308b <\/label>","<span><\/span> <label> <input type=\"radio\" name=\"question_349_4291\" value=\"2\"><a aria-describedby=\"tt\" href=\"https:\/\/tuhoconline.net\/tu-dien-tieng-nhat\/%e4%b8%80\" target=\"_blank\">\u4e00<\/a><a aria-describedby=\"tt\" href=\"https:\/\/tuhoconline.net\/tu-dien-tieng-nhat\/%e6%96%b9\" target=\"_blank\">\u65b9<\/a>\u3067 <\/label>","<span><\/span> <label> <input type=\"radio\" name=\"question_349_4291\" value=\"3\"> \u53b3\u3057\u304f <\/label>","<span><\/span> <label> <input type=\"radio\" name=\"question_349_4291\" value=\"4\"><a aria-describedby=\"tt\" href=\"https:\/\/tuhoconline.net\/tu-dien-tieng-nhat\/%e8%a6%aa\" target=\"_blank\">\u89aa<\/a>\u306f <\/label>"],"answers":[0],"suggestion":null,"solution":null,"sub_quizzes":[]},{"type":"choices","source_title":null,"url":null,"keywords":[],"pre_content":null,"content":"<p><strong><a aria-describedby=\"tt\" target=\"_blank\">\u6b21<\/a>\u306e<a aria-describedby=\"tt\" target=\"_blank\">\u6587<\/a>\u306e\uff3f\u2605\uff3f\u306b\u3082\u3063\u3068\u3082\u3088\u3044\u3082\u306e\u3092\u3001\uff11\u30fb\uff12\u30fb\uff13\u30fb\uff14\u304b\u3089<a aria-describedby=\"tt\" target=\"_blank\">\u4e00<\/a>\u3064\u3048\u3089\u3073\u306a\u3055\u3044<\/strong><\/p>\n<p>\uff3f\uff3f\u3000\uff3f\uff3f\u3000\uff3f\uff3f\u3000\uff3f\u2605\uff3f\u3000\u3057\u307e\u3063\u305f\u3002<\/p>","choices":["<span><\/span> <label> <input type=\"radio\" name=\"question_349_4292\" value=\"1\"><a aria-describedby=\"tt\" href=\"https:\/\/tuhoconline.net\/tu-dien-tieng-nhat\/%e5%af%9d\" target=\"_blank\">\u5bdd<\/a>\u3066 <\/label>","<span><\/span> <label> <input type=\"radio\" name=\"question_349_4292\" value=\"2\"> \u30c6\u30ec\u30d3\u3092 <\/label>","<span><\/span> <label> <input type=\"radio\" name=\"question_349_4292\" value=\"3\"> \u3067 <\/label>","<span><\/span> <label> <input type=\"radio\" name=\"question_349_4292\" value=\"4\"> \u3064\u3051\u3063\u3071\u306a\u3057 <\/label>"],"answers":[0],"suggestion":null,"solution":null,"sub_quizzes":[]},{"type":"choices","source_title":null,"url":null,"keywords":[],"pre_content":null,"content":"<p><strong><a aria-describedby=\"tt\" target=\"_blank\">\u6b21<\/a>\u306e<a aria-describedby=\"tt\" target=\"_blank\">\u6587<\/a>\u306e\uff3f\u2605\uff3f\u306b\u3082\u3063\u3068\u3082\u3088\u3044\u3082\u306e\u3092\u3001\uff11\u30fb\uff12\u30fb\uff13\u30fb\uff14\u304b\u3089<a aria-describedby=\"tt\" target=\"_blank\">\u4e00<\/a>\u3064\u3048\u3089\u3073\u306a\u3055\u3044<\/strong><\/p>\n<p><a aria-describedby=\"tt\" target=\"_blank\">\u666f<\/a><a aria-describedby=\"tt\" target=\"_blank\">\u6c17<\/a>\u304c<a aria-describedby=\"tt\" target=\"_blank\">\u60aa<\/a>\u304f\u3066\u3001\uff3f\uff3f\uff3f\u3001\uff3f\uff3f\u3000\uff3f\uff3f\u3000\uff3f\u2605\uff3f\u3002<\/p>","choices":["<span><\/span> <label> <input type=\"radio\" name=\"question_349_4293\" value=\"1\"><a aria-describedby=\"tt\" href=\"https:\/\/tuhoconline.net\/tu-dien-tieng-nhat\/%e4%b8%80\" target=\"_blank\">\u4e00<\/a><a aria-describedby=\"tt\" href=\"https:\/\/tuhoconline.net\/tu-dien-tieng-nhat\/%e6%96%b9\" target=\"_blank\">\u65b9<\/a>\u3060 <\/label>","<span><\/span> <label> <input type=\"radio\" name=\"question_349_4293\" value=\"2\"> \u3042\u304c\u308b <\/label>","<span><\/span> <label> <input type=\"radio\" name=\"question_349_4293\" value=\"3\"> \u3053\u3053<a aria-describedby=\"tt\" href=\"https:\/\/tuhoconline.net\/tu-dien-tieng-nhat\/%e6%95%b0\" target=\"_blank\">\u6570<\/a><a aria-describedby=\"tt\" href=\"https:\/\/tuhoconline.net\/tu-dien-tieng-nhat\/%e5%b9%b4\" target=\"_blank\">\u5e74<\/a> <\/label>","<span><\/span> <label> <input type=\"radio\" name=\"question_349_4293\" value=\"4\"><a aria-describedby=\"tt\" href=\"https:\/\/tuhoconline.net\/tu-dien-tieng-nhat\/%e5%a4%b1\" target=\"_blank\">\u5931<\/a><a aria-describedby=\"tt\" href=\"https:\/\/tuhoconline.net\/tu-dien-tieng-nhat\/%e6%a5%ad\" target=\"_blank\">\u696d<\/a>\u7387\u306f <\/label>"],"answers":[0],"suggestion":null,"solution":null,"sub_quizzes":[]},{"type":"choices","source_title":null,"url":null,"keywords":[],"pre_content":null,"content":"<p><strong><a aria-describedby=\"tt\" target=\"_blank\">\u6b21<\/a>\u306e<a aria-describedby=\"tt\" target=\"_blank\">\u6587<\/a>\u306e\uff3f\u2605\uff3f\u306b\u3082\u3063\u3068\u3082\u3088\u3044\u3082\u306e\u3092\u3001\uff11\u30fb\uff12\u30fb\uff13\u30fb\uff14\u304b\u3089<a aria-describedby=\"tt\" target=\"_blank\">\u4e00<\/a>\u3064\u3048\u3089\u3073\u306a\u3055\u3044<\/strong><\/p>\n<p>\uff3f\uff3f\u3000\uff3f\uff3f\u3000\uff3f\u2605\uff3f\u3000\uff3f\uff3f\u3000\u3057\u305f\u3002<\/p>","choices":["<span><\/span> <label> <input type=\"radio\" name=\"question_349_4294\" value=\"1\"><a aria-describedby=\"tt\" href=\"https:\/\/tuhoconline.net\/tu-dien-tieng-nhat\/%e7%9b%ae\" target=\"_blank\">\u76ee<\/a>\u3064\u304d <\/label>","<span><\/span> <label> <input type=\"radio\" name=\"question_349_4294\" value=\"2\"> <a aria-describedby=\"tt\" href=\"https:\/\/tuhoconline.net\/tu-dien-tieng-nhat\/%e5%bd%bc\" target=\"_blank\">\u5f7c<\/a>\u306f <\/label>","<span><\/span> <label> <input type=\"radio\" name=\"question_349_4294\" value=\"3\"> \u3044\u305f\u305a\u3089\u3063\u307d\u3044 <\/label>","<span><\/span> <label> <input type=\"radio\" name=\"question_349_4294\" value=\"4\"> \u3092 <\/label>"],"answers":[0],"suggestion":null,"solution":null,"sub_quizzes":[]},{"type":"choices","source_title":null,"url":null,"keywords":[],"pre_content":null,"content":"<p><strong><a aria-describedby=\"tt\" target=\"_blank\">\u6b21<\/a>\u306e<a aria-describedby=\"tt\" target=\"_blank\">\u6587<\/a>\u306e\uff3f\u2605\uff3f\u306b\u3082\u3063\u3068\u3082\u3088\u3044\u3082\u306e\u3092\u3001\uff11\u30fb\uff12\u30fb\uff13\u30fb\uff14\u304b\u3089<a aria-describedby=\"tt\" target=\"_blank\">\u4e00<\/a>\u3064\u3048\u3089\u3073\u306a\u3055\u3044<\/strong><\/p>\n<p>\u3053\u306e\u3000\uff3f\uff3f\u3000\uff3f\u2605\uff3f\u3000\uff3f\uff3f\u3001\uff3f\uff3f\u3000\u3053\u3068\u3092<a aria-describedby=\"tt\" target=\"_blank\">\u601d<\/a>\u3044<a aria-describedby=\"tt\" target=\"_blank\">\u51fa<\/a>\u3059\u3002<\/p>","choices":["<span><\/span> <label> <input type=\"radio\" name=\"question_349_4295\" value=\"1\"><a aria-describedby=\"tt\" href=\"https:\/\/tuhoconline.net\/tu-dien-tieng-nhat\/%e8%aa%ad\" target=\"_blank\">\u8aad<\/a>\u3080 <\/label>","<span><\/span> <label> <input type=\"radio\" name=\"question_349_4295\" value=\"2\"> <a aria-describedby=\"tt\" href=\"https:\/\/tuhoconline.net\/tu-dien-tieng-nhat\/%e5%bd%bc\" target=\"_blank\">\u5f7c<\/a>\u306e <\/label>","<span><\/span> <label> <input type=\"radio\" name=\"question_349_4295\" value=\"3\"><a aria-describedby=\"tt\" href=\"https:\/\/tuhoconline.net\/tu-dien-tieng-nhat\/%e6%9c%ac\" target=\"_blank\">\u672c<\/a>\u3092 <\/label>","<span><\/span> <label> <input type=\"radio\" name=\"question_349_4295\" value=\"4\"> \u305f\u3073\u306b <\/label>"],"answers":[0],"suggestion":null,"solution":null,"sub_quizzes":[]},{"type":"choices","source_title":null,"url":null,"keywords":[],"pre_content":null,"content":"<p><strong><a aria-describedby=\"tt\" target=\"_blank\">\u6b21<\/a>\u306e<a aria-describedby=\"tt\" target=\"_blank\">\u6587<\/a>\u306e\uff3f\u2605\uff3f\u306b\u3082\u3063\u3068\u3082\u3088\u3044\u3082\u306e\u3092\u3001\uff11\u30fb\uff12\u30fb\uff13\u30fb\uff14\u304b\u3089<a aria-describedby=\"tt\" target=\"_blank\">\u4e00<\/a>\u3064\u3048\u3089\u3073\u306a\u3055\u3044<\/strong><\/p>\n<p>\uff3f\uff3f\u3000\uff3f\uff3f\u3001\uff3f\uff3f\u3000\uff3f\u2605\uff3f\u3000\u3092<a aria-describedby=\"tt\" target=\"_blank\">\u6d41<\/a>\u3057\u307e\u3057\u305f\u3002<\/p>","choices":["<span><\/span> <label> <input type=\"radio\" name=\"question_349_4296\" value=\"1\"><a aria-describedby=\"tt\" href=\"https:\/\/tuhoconline.net\/tu-dien-tieng-nhat\/%e6%b6%99\" target=\"_blank\">\u6d99<\/a> <\/label>","<span><\/span> <label> <input type=\"radio\" name=\"question_349_4296\" value=\"2\"> \u3046\u308c\u3057\u3055\u306e <\/label>","<span><\/span> <label> <input type=\"radio\" name=\"question_349_4296\" value=\"3\"> <a aria-describedby=\"tt\" href=\"https:\/\/tuhoconline.net\/tu-dien-tieng-nhat\/%e5%bd%bc\" target=\"_blank\">\u5f7c<\/a>\u306f <\/label>","<span><\/span> <label> <input type=\"radio\" name=\"question_349_4296\" value=\"4\"> \u3042\u307e\u308a <\/label>"],"answers":[0],"suggestion":null,"solution":null,"sub_quizzes":[]},{"type":"choices","source_title":null,"url":null,"keywords":[],"pre_content":null,"content":"<p><strong><a aria-describedby=\"tt\" target=\"_blank\">\u6b21<\/a>\u306e<a aria-describedby=\"tt\" target=\"_blank\">\u6587<\/a>\u306e\uff3f\u2605\uff3f\u306b\u3082\u3063\u3068\u3082\u3088\u3044\u3082\u306e\u3092\u3001\uff11\u30fb\uff12\u30fb\uff13\u30fb\uff14\u304b\u3089<a aria-describedby=\"tt\" target=\"_blank\">\u4e00<\/a>\u3064\u3048\u3089\u3073\u306a\u3055\u3044<\/strong><\/p>\n<p><a aria-describedby=\"tt\" target=\"_blank\">\u4f55<\/a>\u304b<a aria-describedby=\"tt\" target=\"_blank\">\u98df<\/a>\u3079\u306b<a aria-describedby=\"tt\" target=\"_blank\">\u884c<\/a>\u3053\u3046\u3002\uff3f\uff3f\u3000\uff3f\u2605\uff3f\u3000\uff3f\uff3f\u3000\uff3f\uff3f\u3000\u3057\u3088\u3046\u3002<\/p>","choices":["<span><\/span> <label> <input type=\"radio\" name=\"question_349_4297\" value=\"1\"><a aria-describedby=\"tt\" href=\"https:\/\/tuhoconline.net\/tu-dien-tieng-nhat\/%e8%b2%b7\" target=\"_blank\">\u8cb7<\/a>\u3044<a aria-describedby=\"tt\" href=\"https:\/\/tuhoconline.net\/tu-dien-tieng-nhat\/%e7%89%a9\" target=\"_blank\">\u7269<\/a> <\/label>","<span><\/span> <label> <input type=\"radio\" name=\"question_349_4297\" value=\"2\"> \u3082 <\/label>","<span><\/span> <label> <input type=\"radio\" name=\"question_349_4297\" value=\"3\"> \u3064\u3044\u3067\u306b <\/label>","<span><\/span> <label> <input type=\"radio\" name=\"question_349_4297\" value=\"4\"><a aria-describedby=\"tt\" href=\"https:\/\/tuhoconline.net\/tu-dien-tieng-nhat\/%e5%85%88\" target=\"_blank\">\u5148<\/a>\u306b <\/label>"],"answers":[0],"suggestion":null,"solution":null,"sub_quizzes":[]},{"type":"choices","source_title":null,"url":null,"keywords":[],"pre_content":null,"content":"<p><strong><a aria-describedby=\"tt\" target=\"_blank\">\u6b21<\/a>\u306e<a aria-describedby=\"tt\" target=\"_blank\">\u6587<\/a>\u306e\uff3f\u2605\uff3f\u306b\u3082\u3063\u3068\u3082\u3088\u3044\u3082\u306e\u3092\u3001\uff11\u30fb\uff12\u30fb\uff13\u30fb\uff14\u304b\u3089<a aria-describedby=\"tt\" target=\"_blank\">\u4e00<\/a>\u3064\u3048\u3089\u3073\u306a\u3055\u3044<\/strong><\/p>\n<p>\u308f\u305f\u3057\u306e<a aria-describedby=\"tt\" target=\"_blank\">\u4ed5<\/a><a aria-describedby=\"tt\" target=\"_blank\">\u4e8b<\/a>\u306f\uff3f\uff3f\u3000\uff3f\uff3f\u3000\uff3f\u2605\uff3f\u3000\uff3f\uff3f\u3001<a aria-describedby=\"tt\" target=\"_blank\">\u51ac<\/a>\u306f\u6687\u306b\u306a\u308b\u3002<\/p>","choices":["<span><\/span> <label> <input type=\"radio\" name=\"question_349_4298\" value=\"1\"><a aria-describedby=\"tt\" href=\"https:\/\/tuhoconline.net\/tu-dien-tieng-nhat\/%e5%bf%99\" target=\"_blank\">\u5fd9<\/a>\u3057\u3044 <\/label>","<span><\/span> <label> <input type=\"radio\" name=\"question_349_4298\" value=\"2\"><a aria-describedby=\"tt\" href=\"https:\/\/tuhoconline.net\/tu-dien-tieng-nhat\/%e4%b8%80\" target=\"_blank\">\u4e00<\/a><a aria-describedby=\"tt\" href=\"https:\/\/tuhoconline.net\/tu-dien-tieng-nhat\/%e6%96%b9\" target=\"_blank\">\u65b9<\/a> <\/label>","<span><\/span> <label> <input type=\"radio\" name=\"question_349_4298\" value=\"3\"><a aria-describedby=\"tt\" href=\"https:\/\/tuhoconline.net\/tu-dien-tieng-nhat\/%e5%a4%8f\" target=\"_blank\">\u590f<\/a>\u306f <\/label>","<span><\/span> <label> <input type=\"radio\" name=\"question_349_4298\" value=\"4\"><a aria-describedby=\"tt\" href=\"https:\/\/tuhoconline.net\/tu-dien-tieng-nhat\/%e9%9d%9e\" target=\"_blank\">\u975e<\/a><a aria-describedby=\"tt\" href=\"https:\/\/tuhoconline.net\/tu-dien-tieng-nhat\/%e5%b8%b8\" target=\"_blank\">\u5e38<\/a>\u306b <\/label>"],"answers":[0],"suggestion":null,"solution":null,"sub_quizzes":[]},{"type":"choices","source_title":null,"url":null,"keywords":[],"pre_content":null,"content":"<p><strong><a aria-describedby=\"tt\" target=\"_blank\">\u6b21<\/a>\u306e<a aria-describedby=\"tt\" target=\"_blank\">\u6587<\/a>\u306e\uff3f\u2605\uff3f\u306b\u3082\u3063\u3068\u3082\u3088\u3044\u3082\u306e\u3092\u3001\uff11\u30fb\uff12\u30fb\uff13\u30fb\uff14\u304b\u3089<a aria-describedby=\"tt\" target=\"_blank\">\u4e00<\/a>\u3064\u3048\u3089\u3073\u306a\u3055\u3044<\/strong><\/p>\n<p><a aria-describedby=\"tt\" target=\"_blank\">\u7533<\/a>\u3057\u8a33\u306a\u3044\u3093\u3067\u3001\uff3f\uff3f\u3000\uff3f\u2605\uff3f\u3000\uff3f\uff3f\u3000\uff3f\uff3f\u3000<a aria-describedby=\"tt\" target=\"_blank\">\u571f<\/a><a aria-describedby=\"tt\" target=\"_blank\">\u66dc<\/a><a aria-describedby=\"tt\" target=\"_blank\">\u65e5<\/a>\u306b\u3082<a aria-describedby=\"tt\" target=\"_blank\">\u51fa<\/a>\u3066<a aria-describedby=\"tt\" target=\"_blank\">\u6765<\/a>\u3066\u3082\u3089\u3046\u304b\u3068<a aria-describedby=\"tt\" target=\"_blank\">\u601d<\/a>\u3063\u3066\u3002<\/p>","choices":["<span><\/span> <label> <input type=\"radio\" name=\"question_349_4299\" value=\"1\"><a aria-describedby=\"tt\" href=\"https:\/\/tuhoconline.net\/tu-dien-tieng-nhat\/%e5%90%9b\" target=\"_blank\">\u541b<\/a> <\/label>","<span><\/span> <label> <input type=\"radio\" name=\"question_349_4299\" value=\"2\"> \u3082\u3057 <\/label>","<span><\/span> <label> <input type=\"radio\" name=\"question_349_4299\" value=\"3\"> \u3055\u3048 <\/label>","<span><\/span> <label> <input type=\"radio\" name=\"question_349_4299\" value=\"4\"><a aria-describedby=\"tt\" href=\"https:\/\/tuhoconline.net\/tu-dien-tieng-nhat\/%e8%89%af\" target=\"_blank\">\u826f<\/a>\u3051\u308c\u3070 <\/label>"],"answers":[0],"suggestion":null,"solution":null,"sub_quizzes":[]},{"type":"choices","source_title":null,"url":null,"keywords":[],"pre_content":null,"content":"<p><strong><a aria-describedby=\"tt\" target=\"_blank\">\u6b21<\/a>\u306e<a aria-describedby=\"tt\" target=\"_blank\">\u6587<\/a>\u306e\uff3f\u2605\uff3f\u306b\u3082\u3063\u3068\u3082\u3088\u3044\u3082\u306e\u3092\u3001\uff11\u30fb\uff12\u30fb\uff13\u30fb\uff14\u304b\u3089<a aria-describedby=\"tt\" target=\"_blank\">\u4e00<\/a>\u3064\u3048\u3089\u3073\u306a\u3055\u3044<\/strong><\/p>\n<p><a aria-describedby=\"tt\" target=\"_blank\">\u5f7c<\/a><a aria-describedby=\"tt\" target=\"_blank\">\u5973<\/a>\u306f<a aria-describedby=\"tt\" target=\"_blank\">\u5b66<\/a><a aria-describedby=\"tt\" target=\"_blank\">\u751f<\/a>\u306e\uff3f\uff3f\u3000\uff3f\u2605\uff3f\u3000\uff3f\uff3f\u3000\uff3f\uff3f\u3000\u3092<a aria-describedby=\"tt\" target=\"_blank\">\u5bb6<\/a>\u3078<a aria-describedby=\"tt\" target=\"_blank\">\u6301<\/a>\u3061<a aria-describedby=\"tt\" target=\"_blank\">\u5e30<\/a>\u3057\u3066\u3001\u3044\u3061\u3044\u3061<a aria-describedby=\"tt\" target=\"_blank\">\u76f4<\/a>\u3057\u3066\u3084\u308a\u307e\u3057\u305f\u3002<\/p>","choices":["<span><\/span> <label> <input type=\"radio\" name=\"question_349_4300\" value=\"1\"> \u3060\u3089\u3051 <\/label>","<span><\/span> <label> <input type=\"radio\" name=\"question_349_4300\" value=\"2\"><a aria-describedby=\"tt\" href=\"https:\/\/tuhoconline.net\/tu-dien-tieng-nhat\/%e4%bd%9c\" target=\"_blank\">\u4f5c<\/a><a aria-describedby=\"tt\" href=\"https:\/\/tuhoconline.net\/tu-dien-tieng-nhat\/%e6%96%87\" target=\"_blank\">\u6587<\/a> <\/label>","<span><\/span> <label> <input type=\"radio\" name=\"question_349_4300\" value=\"3\"> \u306e <\/label>","<span><\/span> <label> <input type=\"radio\" name=\"question_349_4300\" value=\"4\"><a aria-describedby=\"tt\" href=\"https:\/\/tuhoconline.net\/tu-dien-tieng-nhat\/%e9%96%93\" target=\"_blank\">\u9593<\/a><a aria-describedby=\"tt\" href=\"https:\/\/tuhoconline.net\/tu-dien-tieng-nhat\/%e9%81%95\" target=\"_blank\">\u9055<\/a>\u3044 <\/label>"],"answers":[0],"suggestion":null,"solution":null,"sub_quizzes":[]}]}