{"title":"\u0111\u1ec1 thi n\u0103ng l\u1ef1c ti\u1ebfng Nh\u1eadt N3 \u0111\u1ec1 s\u1ed1\u00a078","url":"https:\/\/tuhoconline.net\/de-thi-nang-luc-tieng-nhat-n3-de-so-78.html","keywords":["\u0110\u1ec1 thi N3","Luy\u1ec7n thi N3"],"quizzes":[{"type":"choices","source_title":null,"url":null,"keywords":[],"pre_content":null,"content":"<p><strong><a aria-describedby=\"tt\" target=\"_blank\">\u6b21<\/a>\u306e<a aria-describedby=\"tt\" target=\"_blank\">\u6587<\/a>\u306e\uff3f\u2605\uff3f\u306b\u3082\u3063\u3068\u3082\u3088\u3044\u3082\u306e\u3092\u3001\uff11\u30fb\uff12\u30fb\uff13\u30fb\uff14\u304b\u3089<a aria-describedby=\"tt\" target=\"_blank\">\u4e00<\/a>\u3064\u3048\u3089\u3073\u306a\u3055\u3044<\/strong><\/p>\n<p><a aria-describedby=\"tt\" target=\"_blank\">\u4f53<\/a>\u3092\u4e08<a aria-describedby=\"tt\" target=\"_blank\">\u592b<\/a>\u306b\u3057\u305f\u304b\u3063\u305f\u3089\u3001<a aria-describedby=\"tt\" target=\"_blank\">\u597d<\/a>\u304d\u5acc\u3044\u3092\uff3f\uff3f\u3000\uff3f\uff3f\u3000\uff3f\u2605\uff3f\u3000\uff3f\uff3f\u3002<\/p>","choices":["<span><\/span> <label> <input type=\"radio\" name=\"question_360_4401\" value=\"1\"><a aria-describedby=\"tt\" href=\"https:\/\/tuhoconline.net\/tu-dien-tieng-nhat\/%e9%a3%9f\" target=\"_blank\">\u98df<\/a>\u3079\u308b <\/label>","<span><\/span> <label> <input type=\"radio\" name=\"question_360_4401\" value=\"2\"> \u3053\u3068\u3060 <\/label>","<span><\/span> <label> <input type=\"radio\" name=\"question_360_4401\" value=\"3\"> \u3057\u306a\u3044\u3067 <\/label>","<span><\/span> <label> <input type=\"radio\" name=\"question_360_4401\" value=\"4\"><a aria-describedby=\"tt\" href=\"https:\/\/tuhoconline.net\/tu-dien-tieng-nhat\/%e4%bd%95\" target=\"_blank\">\u4f55<\/a>\u3067\u3082 <\/label>"],"answers":[0],"suggestion":null,"solution":null,"sub_quizzes":[]},{"type":"choices","source_title":null,"url":null,"keywords":[],"pre_content":null,"content":"<p><strong><a aria-describedby=\"tt\" target=\"_blank\">\u6b21<\/a>\u306e<a aria-describedby=\"tt\" target=\"_blank\">\u6587<\/a>\u306e\uff3f\u2605\uff3f\u306b\u3082\u3063\u3068\u3082\u3088\u3044\u3082\u306e\u3092\u3001\uff11\u30fb\uff12\u30fb\uff13\u30fb\uff14\u304b\u3089<a aria-describedby=\"tt\" target=\"_blank\">\u4e00<\/a>\u3064\u3048\u3089\u3073\u306a\u3055\u3044<\/strong><\/p>\n<p><a aria-describedby=\"tt\" target=\"_blank\">\u8aad<\/a><a aria-describedby=\"tt\" target=\"_blank\">\u89e3<\/a><a aria-describedby=\"tt\" target=\"_blank\">\u529b<\/a>\u3092\u3064\u3051\u305f\u3044\u306e\u306a\u3089\u3001\uff3f\uff3f\u3000\uff3f\uff3f\u3000\uff3f\u2605\uff3f\u3000\uff3f\uff3f\u3002<\/p>","choices":["<span><\/span> <label> <input type=\"radio\" name=\"question_360_4402\" value=\"1\"> \u3092 <\/label>","<span><\/span> <label> <input type=\"radio\" name=\"question_360_4402\" value=\"2\"><a aria-describedby=\"tt\" href=\"https:\/\/tuhoconline.net\/tu-dien-tieng-nhat\/%e6%96%b0\" target=\"_blank\">\u65b0<\/a><a aria-describedby=\"tt\" href=\"https:\/\/tuhoconline.net\/tu-dien-tieng-nhat\/%e8%81%9e\" target=\"_blank\">\u805e<\/a> <\/label>","<span><\/span> <label> <input type=\"radio\" name=\"question_360_4402\" value=\"3\"><a aria-describedby=\"tt\" href=\"https:\/\/tuhoconline.net\/tu-dien-tieng-nhat\/%e8%aa%ad\" target=\"_blank\">\u8aad<\/a>\u3080\u3053\u3068\u3060 <\/label>","<span><\/span> <label> <input type=\"radio\" name=\"question_360_4402\" value=\"4\"><a aria-describedby=\"tt\" href=\"https:\/\/tuhoconline.net\/tu-dien-tieng-nhat\/%e6%af%8e\" target=\"_blank\">\u6bce<\/a><a aria-describedby=\"tt\" href=\"https:\/\/tuhoconline.net\/tu-dien-tieng-nhat\/%e6%97%a5\" target=\"_blank\">\u65e5<\/a> <\/label>"],"answers":[0],"suggestion":null,"solution":null,"sub_quizzes":[]},{"type":"choices","source_title":null,"url":null,"keywords":[],"pre_content":null,"content":"<p><strong><a aria-describedby=\"tt\" target=\"_blank\">\u6b21<\/a>\u306e<a aria-describedby=\"tt\" target=\"_blank\">\u6587<\/a>\u306e\uff3f\u2605\uff3f\u306b\u3082\u3063\u3068\u3082\u3088\u3044\u3082\u306e\u3092\u3001\uff11\u30fb\uff12\u30fb\uff13\u30fb\uff14\u304b\u3089<a aria-describedby=\"tt\" target=\"_blank\">\u4e00<\/a>\u3064\u3048\u3089\u3073\u306a\u3055\u3044<\/strong><\/p>\n<p>\u308f\u305f\u3057\u304c\u3053\u3053\u306b\u3044\u308b\u304b\u304e\u308a\u3001<a aria-describedby=\"tt\" target=\"_blank\">\u4f55<\/a><a aria-describedby=\"tt\" target=\"_blank\">\u7269<\/a>\u3082\uff3f\uff3f\u3000\uff3f\u2605\uff3f\u3000\uff3f\uff3f\u3000\uff3f\uff3f\u3000\u3068<a aria-describedby=\"tt\" target=\"_blank\">\u601d<\/a>\u3044\u305f\u307e\u3048\u3002<\/p>","choices":["<span><\/span> <label> <input type=\"radio\" name=\"question_360_4403\" value=\"1\"><a aria-describedby=\"tt\" href=\"https:\/\/tuhoconline.net\/tu-dien-tieng-nhat\/%e5%8d%b1\" target=\"_blank\">\u5371<\/a>\u5bb3\u3092 <\/label>","<span><\/span> <label> <input type=\"radio\" name=\"question_360_4403\" value=\"2\"><a aria-describedby=\"tt\" href=\"https:\/\/tuhoconline.net\/tu-dien-tieng-nhat\/%e5%8a%a0\" target=\"_blank\">\u52a0<\/a>\u3048\u308b <\/label>","<span><\/span> <label> <input type=\"radio\" name=\"question_360_4403\" value=\"3\"><a aria-describedby=\"tt\" href=\"https:\/\/tuhoconline.net\/tu-dien-tieng-nhat\/%e5%90%9b\" target=\"_blank\">\u541b<\/a>\u305f\u3061\u306b <\/label>","<span><\/span> <label> <input type=\"radio\" name=\"question_360_4403\" value=\"4\"> \u3053\u3068\u306f\u306a\u3044 <\/label>"],"answers":[0],"suggestion":null,"solution":null,"sub_quizzes":[]},{"type":"choices","source_title":null,"url":null,"keywords":[],"pre_content":null,"content":"<p><strong><a aria-describedby=\"tt\" target=\"_blank\">\u6b21<\/a>\u306e<a aria-describedby=\"tt\" target=\"_blank\">\u6587<\/a>\u306e\uff3f\u2605\uff3f\u306b\u3082\u3063\u3068\u3082\u3088\u3044\u3082\u306e\u3092\u3001\uff11\u30fb\uff12\u30fb\uff13\u30fb\uff14\u304b\u3089<a aria-describedby=\"tt\" target=\"_blank\">\u4e00<\/a>\u3064\u3048\u3089\u3073\u306a\u3055\u3044<\/strong><\/p>\n<p><a aria-describedby=\"tt\" target=\"_blank\">\u82f1<\/a><a aria-describedby=\"tt\" target=\"_blank\">\u8a9e<\/a>\u306e<a aria-describedby=\"tt\" target=\"_blank\">\u6587<\/a><a aria-describedby=\"tt\" target=\"_blank\">\u6cd5<\/a>\u306f\uff3f\uff3f\u3000\uff3f\uff3f\u3000\uff3f\u2605\uff3f\u3000\uff3f\uff3f\u3002<\/p>","choices":["<span><\/span> <label> <input type=\"radio\" name=\"question_360_4404\" value=\"1\"><a aria-describedby=\"tt\" href=\"https:\/\/tuhoconline.net\/tu-dien-tieng-nhat\/%e9%9b%a3\" target=\"_blank\">\u96e3<\/a>\u3057\u304f <\/label>","<span><\/span> <label> <input type=\"radio\" name=\"question_360_4404\" value=\"2\"> \u307b\u3069 <\/label>","<span><\/span> <label> <input type=\"radio\" name=\"question_360_4404\" value=\"3\"> \u3042\u308a\u307e\u305b\u3093 <\/label>","<span><\/span> <label> <input type=\"radio\" name=\"question_360_4404\" value=\"4\"><a aria-describedby=\"tt\" href=\"https:\/\/tuhoconline.net\/tu-dien-tieng-nhat\/%e6%97%a5\" target=\"_blank\">\u65e5<\/a><a aria-describedby=\"tt\" href=\"https:\/\/tuhoconline.net\/tu-dien-tieng-nhat\/%e6%9c%ac\" target=\"_blank\">\u672c<\/a><a aria-describedby=\"tt\" href=\"https:\/\/tuhoconline.net\/tu-dien-tieng-nhat\/%e8%aa%9e\" target=\"_blank\">\u8a9e<\/a> <\/label>"],"answers":[0],"suggestion":null,"solution":null,"sub_quizzes":[]},{"type":"choices","source_title":null,"url":null,"keywords":[],"pre_content":null,"content":"<p><strong><a aria-describedby=\"tt\" target=\"_blank\">\u6b21<\/a>\u306e<a aria-describedby=\"tt\" target=\"_blank\">\u6587<\/a>\u306e\uff3f\u2605\uff3f\u306b\u3082\u3063\u3068\u3082\u3088\u3044\u3082\u306e\u3092\u3001\uff11\u30fb\uff12\u30fb\uff13\u30fb\uff14\u304b\u3089<a aria-describedby=\"tt\" target=\"_blank\">\u4e00<\/a>\u3064\u3048\u3089\u3073\u306a\u3055\u3044<\/strong><\/p>\n<p>\u308f\u305f\u3057\u306f<a aria-describedby=\"tt\" target=\"_blank\">\u8089<\/a>\u306f\u3000\uff3f\u2605\uff3f\u3002\uff3f\uff3f\u3001\uff3f\uff3f\u3000\uff3f\uff3f\u3000\u3067\u3059\u3002<\/p>","choices":["<span><\/span> <label> <input type=\"radio\" name=\"question_360_4405\" value=\"1\"><a aria-describedby=\"tt\" href=\"https:\/\/tuhoconline.net\/tu-dien-tieng-nhat\/%e9%a3%9f\" target=\"_blank\">\u98df<\/a>\u3079\u307e\u305b\u3093 <\/label>","<span><\/span> <label> <input type=\"radio\" name=\"question_360_4405\" value=\"2\"><a aria-describedby=\"tt\" href=\"https:\/\/tuhoconline.net\/tu-dien-tieng-nhat\/%e8%8f%9c\" target=\"_blank\">\u83dc<\/a><a aria-describedby=\"tt\" href=\"https:\/\/tuhoconline.net\/tu-dien-tieng-nhat\/%e9%a3%9f\" target=\"_blank\">\u98df<\/a><a aria-describedby=\"tt\" href=\"https:\/\/tuhoconline.net\/tu-dien-tieng-nhat\/%e4%b8%bb\" target=\"_blank\">\u4e3b<\/a><a aria-describedby=\"tt\" href=\"https:\/\/tuhoconline.net\/tu-dien-tieng-nhat\/%e7%be%a9\" target=\"_blank\">\u7fa9<\/a> <\/label>","<span><\/span> <label> <input type=\"radio\" name=\"question_360_4405\" value=\"3\"> \u3060\u304b\u3089 <\/label>","<span><\/span> <label> <input type=\"radio\" name=\"question_360_4405\" value=\"4\"> \u3068\u3044\u3046\u306e\u306f <\/label>"],"answers":[0],"suggestion":null,"solution":null,"sub_quizzes":[]},{"type":"choices","source_title":null,"url":null,"keywords":[],"pre_content":null,"content":"<p><strong><a aria-describedby=\"tt\" target=\"_blank\">\u6b21<\/a>\u306e<a aria-describedby=\"tt\" target=\"_blank\">\u6587<\/a>\u306e\uff3f\u2605\uff3f\u306b\u3082\u3063\u3068\u3082\u3088\u3044\u3082\u306e\u3092\u3001\uff11\u30fb\uff12\u30fb\uff13\u30fb\uff14\u304b\u3089<a aria-describedby=\"tt\" target=\"_blank\">\u4e00<\/a>\u3064\u3048\u3089\u3073\u306a\u3055\u3044<\/strong><\/p>\n<p>\uff3f\uff3f\u3000\uff3f\uff3f\u3000\uff3f\uff3f\u3000\uff3f\u2605\uff3f\u3000\u304b\u3082\u3057\u308c\u306a\u3044\u3002<\/p>","choices":["<span><\/span> <label> <input type=\"radio\" name=\"question_360_4406\" value=\"1\"> \u3084\u3081\u305f <\/label>","<span><\/span> <label> <input type=\"radio\" name=\"question_360_4406\" value=\"2\"> <a aria-describedby=\"tt\" href=\"https:\/\/tuhoconline.net\/tu-dien-tieng-nhat\/%e5%bd%bc\" target=\"_blank\">\u5f7c<\/a>\u306f <\/label>","<span><\/span> <label> <input type=\"radio\" name=\"question_360_4406\" value=\"3\"> \u3082\u3057\u304b\u3057\u305f\u3089 <\/label>","<span><\/span> <label> <input type=\"radio\" name=\"question_360_4406\" value=\"4\"><a aria-describedby=\"tt\" href=\"https:\/\/tuhoconline.net\/tu-dien-tieng-nhat\/%e4%bc%9a\" target=\"_blank\">\u4f1a<\/a><a aria-describedby=\"tt\" href=\"https:\/\/tuhoconline.net\/tu-dien-tieng-nhat\/%e7%a4%be\" target=\"_blank\">\u793e<\/a>\u3092 <\/label>"],"answers":[0],"suggestion":null,"solution":null,"sub_quizzes":[]},{"type":"choices","source_title":null,"url":null,"keywords":[],"pre_content":null,"content":"<p><strong><a aria-describedby=\"tt\" target=\"_blank\">\u6b21<\/a>\u306e<a aria-describedby=\"tt\" target=\"_blank\">\u6587<\/a>\u306e\uff3f\u2605\uff3f\u306b\u3082\u3063\u3068\u3082\u3088\u3044\u3082\u306e\u3092\u3001\uff11\u30fb\uff12\u30fb\uff13\u30fb\uff14\u304b\u3089<a aria-describedby=\"tt\" target=\"_blank\">\u4e00<\/a>\u3064\u3048\u3089\u3073\u306a\u3055\u3044<\/strong><\/p>\n<p>\u3053\u308c\u306f\u3000\uff3f\uff3f\u3000\uff3f\u2605\uff3f\u3000\uff3f\uff3f\u3000\uff3f\uff3f\u3067\u3059\u3002<\/p>","choices":["<span><\/span> <label> <input type=\"radio\" name=\"question_360_4407\" value=\"1\"><a aria-describedby=\"tt\" href=\"https:\/\/tuhoconline.net\/tu-dien-tieng-nhat\/%e5%90%91\" target=\"_blank\">\u5411<\/a>\u304d <\/label>","<span><\/span> <label> <input type=\"radio\" name=\"question_360_4407\" value=\"2\"> \u306e <\/label>","<span><\/span> <label> <input type=\"radio\" name=\"question_360_4407\" value=\"3\"> \u7ae5<a aria-describedby=\"tt\" href=\"https:\/\/tuhoconline.net\/tu-dien-tieng-nhat\/%e8%a9%b1\" target=\"_blank\">\u8a71<\/a><a aria-describedby=\"tt\" href=\"https:\/\/tuhoconline.net\/tu-dien-tieng-nhat\/%e9%9b%86\" target=\"_blank\">\u96c6<\/a> <\/label>","<span><\/span> <label> <input type=\"radio\" name=\"question_360_4407\" value=\"4\"><a aria-describedby=\"tt\" href=\"https:\/\/tuhoconline.net\/tu-dien-tieng-nhat\/%e5%b0%8f\" target=\"_blank\">\u5c0f<\/a><a aria-describedby=\"tt\" href=\"https:\/\/tuhoconline.net\/tu-dien-tieng-nhat\/%e5%ad%a6\" target=\"_blank\">\u5b66<\/a><a aria-describedby=\"tt\" href=\"https:\/\/tuhoconline.net\/tu-dien-tieng-nhat\/%e7%94%9f\" target=\"_blank\">\u751f<\/a> <\/label>"],"answers":[0],"suggestion":null,"solution":null,"sub_quizzes":[]},{"type":"choices","source_title":null,"url":null,"keywords":[],"pre_content":null,"content":"<p><strong><a aria-describedby=\"tt\" target=\"_blank\">\u6b21<\/a>\u306e<a aria-describedby=\"tt\" target=\"_blank\">\u6587<\/a>\u306e\uff3f\u2605\uff3f\u306b\u3082\u3063\u3068\u3082\u3088\u3044\u3082\u306e\u3092\u3001\uff11\u30fb\uff12\u30fb\uff13\u30fb\uff14\u304b\u3089<a aria-describedby=\"tt\" target=\"_blank\">\u4e00<\/a>\u3064\u3048\u3089\u3073\u306a\u3055\u3044<\/strong><\/p>\n<p><a aria-describedby=\"tt\" target=\"_blank\">\u751f<\/a><a aria-describedby=\"tt\" target=\"_blank\">\u6d3b<\/a>\u304c\uff3f\u2605\uff3f\u3000\uff3f\uff3f\u3000\uff3f\uff3f\uff3f\u3000\uff3f\uff3f\u3000\u3060\u3002<\/p>","choices":["<span><\/span> <label> <input type=\"radio\" name=\"question_360_4408\" value=\"1\"> \u3067 <\/label>","<span><\/span> <label> <input type=\"radio\" name=\"question_360_4408\" value=\"2\"> \u7761<a aria-describedby=\"tt\" href=\"https:\/\/tuhoconline.net\/tu-dien-tieng-nhat\/%e7%9c%a0\" target=\"_blank\">\u7720<\/a><a aria-describedby=\"tt\" href=\"https:\/\/tuhoconline.net\/tu-dien-tieng-nhat\/%e4%b8%8d\" target=\"_blank\">\u4e0d<\/a><a aria-describedby=\"tt\" href=\"https:\/\/tuhoconline.net\/tu-dien-tieng-nhat\/%e8%b6%b3\" target=\"_blank\">\u8db3<\/a> <\/label>","<span><\/span> <label> <input type=\"radio\" name=\"question_360_4408\" value=\"3\"><a aria-describedby=\"tt\" href=\"https:\/\/tuhoconline.net\/tu-dien-tieng-nhat\/%e6%b0%97\" target=\"_blank\">\u6c17<\/a><a aria-describedby=\"tt\" href=\"https:\/\/tuhoconline.net\/tu-dien-tieng-nhat\/%e5%91%b3\" target=\"_blank\">\u5473<\/a> <\/label>","<span><\/span> <label> <input type=\"radio\" name=\"question_360_4408\" value=\"4\"><a aria-describedby=\"tt\" href=\"https:\/\/tuhoconline.net\/tu-dien-tieng-nhat\/%e4%b8%8d\" target=\"_blank\">\u4e0d<\/a><a aria-describedby=\"tt\" href=\"https:\/\/tuhoconline.net\/tu-dien-tieng-nhat\/%e8%a6%8f\" target=\"_blank\">\u898f<\/a>\u5247 <\/label>"],"answers":[0],"suggestion":null,"solution":null,"sub_quizzes":[]},{"type":"choices","source_title":null,"url":null,"keywords":[],"pre_content":null,"content":"<p><strong><a aria-describedby=\"tt\" target=\"_blank\">\u6b21<\/a>\u306e<a aria-describedby=\"tt\" target=\"_blank\">\u6587<\/a>\u306e\uff3f\u2605\uff3f\u306b\u3082\u3063\u3068\u3082\u3088\u3044\u3082\u306e\u3092\u3001\uff11\u30fb\uff12\u30fb\uff13\u30fb\uff14\u304b\u3089<a aria-describedby=\"tt\" target=\"_blank\">\u4e00<\/a>\u3064\u3048\u3089\u3073\u306a\u3055\u3044<\/strong><\/p>\n<p><a aria-describedby=\"tt\" target=\"_blank\">\u5f7c<\/a>\u306f\u305d\u306e<a aria-describedby=\"tt\" target=\"_blank\">\u4e8b<\/a><a aria-describedby=\"tt\" target=\"_blank\">\u4ef6<\/a>\u3092\u3000\uff3f\uff3f\u3000\uff3f\u2605\uff3f\u3000\uff3f\uff3f\u3001\uff3f\uff3f\u3000<a aria-describedby=\"tt\" target=\"_blank\">\u6d99<\/a>\u304c<a aria-describedby=\"tt\" target=\"_blank\">\u51fa<\/a>\u308b\u307b\u3069<a aria-describedby=\"tt\" target=\"_blank\">\u7b11<\/a>\u3046\u3002<\/p>","choices":["<span><\/span> <label> <input type=\"radio\" name=\"question_360_4409\" value=\"1\"><a aria-describedby=\"tt\" href=\"https:\/\/tuhoconline.net\/tu-dien-tieng-nhat\/%e5%87%ba\" target=\"_blank\">\u51fa<\/a>\u3059 <\/label>","<span><\/span> <label> <input type=\"radio\" name=\"question_360_4409\" value=\"2\"> \u3044\u307e\u3067\u3082 <\/label>","<span><\/span> <label> <input type=\"radio\" name=\"question_360_4409\" value=\"3\"> \u305f\u3073\u306b <\/label>","<span><\/span> <label> <input type=\"radio\" name=\"question_360_4409\" value=\"4\"><a aria-describedby=\"tt\" href=\"https:\/\/tuhoconline.net\/tu-dien-tieng-nhat\/%e6%80%9d\" target=\"_blank\">\u601d<\/a>\u3044 <\/label>"],"answers":[0],"suggestion":null,"solution":null,"sub_quizzes":[]},{"type":"choices","source_title":null,"url":null,"keywords":[],"pre_content":null,"content":"<p><strong><a aria-describedby=\"tt\" target=\"_blank\">\u6b21<\/a>\u306e<a aria-describedby=\"tt\" target=\"_blank\">\u6587<\/a>\u306e\uff3f\u2605\uff3f\u306b\u3082\u3063\u3068\u3082\u3088\u3044\u3082\u306e\u3092\u3001\uff11\u30fb\uff12\u30fb\uff13\u30fb\uff14\u304b\u3089<a aria-describedby=\"tt\" target=\"_blank\">\u4e00<\/a>\u3064\u3048\u3089\u3073\u306a\u3055\u3044<\/strong><\/p>\n<p><a aria-describedby=\"tt\" target=\"_blank\">\u96fb<\/a><a aria-describedby=\"tt\" target=\"_blank\">\u8eca<\/a>\u306e<a aria-describedby=\"tt\" target=\"_blank\">\u4e2d<\/a>\u3067\u306f\u3001<a aria-describedby=\"tt\" target=\"_blank\">\u82e5<\/a><a aria-describedby=\"tt\" target=\"_blank\">\u8005<\/a>\u306f\uff3f\uff3f\u3000\uff3f\uff3f\u3000\uff3f\u2605\uff3f\u3000\uff3f\uff3f\u3067\u3059\u3002<\/p>","choices":["<span><\/span> <label> <input type=\"radio\" name=\"question_360_4410\" value=\"1\"> \u8b72\u308b <\/label>","<span><\/span> <label> <input type=\"radio\" name=\"question_360_4410\" value=\"2\"> \u3079\u304d <\/label>","<span><\/span> <label> <input type=\"radio\" name=\"question_360_4410\" value=\"3\"><a aria-describedby=\"tt\" href=\"https:\/\/tuhoconline.net\/tu-dien-tieng-nhat\/%e5%b9%b4\" target=\"_blank\">\u5e74<\/a><a aria-describedby=\"tt\" href=\"https:\/\/tuhoconline.net\/tu-dien-tieng-nhat\/%e5%af%84\" target=\"_blank\">\u5bc4<\/a>\u308a\u306b <\/label>","<span><\/span> <label> <input type=\"radio\" name=\"question_360_4410\" value=\"4\"><a aria-describedby=\"tt\" href=\"https:\/\/tuhoconline.net\/tu-dien-tieng-nhat\/%e5%b8%ad\" target=\"_blank\">\u5e2d<\/a>\u3092 <\/label>"],"answers":[0],"suggestion":null,"solution":null,"sub_quizzes":[]}]}