{"title":"\u0110\u1ec1 thi N1 ti\u1ebfng Nh\u1eadt \u0111\u1ec1 s\u1ed1 38","url":"https:\/\/tuhoconline.net\/de-thi-n1-tieng-nhat-de-so-38.html","keywords":["\u0110\u1ec1 thi N1"],"quizzes":[{"type":"choices","source_title":null,"url":null,"keywords":[],"pre_content":null,"content":"<p><strong><a aria-describedby=\"tt\" target=\"_blank\">\u6b21<\/a>\u306e<a aria-describedby=\"tt\" target=\"_blank\">\u6587<\/a>\u306e\uff3f\u2605\uff3f\u306b\u3082\u3063\u3068\u3082\u3088\u3044\u3082\u306e\u3092\u3001\uff11\u30fb\uff12\u30fb\uff13\u30fb\uff14\u304b\u3089<a aria-describedby=\"tt\" target=\"_blank\">\u4e00<\/a>\u3064\u3048\u3089\u3073\u306a\u3055\u3044<\/strong><\/p>\n<p><a aria-describedby=\"tt\" target=\"_blank\">\u6cf3<\/a>\u3052\u3082\u3057\u306a\u3044\u306e\u306b<a aria-describedby=\"tt\" target=\"_blank\">\u6d77<\/a>\u3078\u3000\uff3f\u2605\uff3f\u3002\uff3f\uff3f\u3000\uff3f\uff3f\u3000\uff3f\uff3f\u3002<\/p>","choices":["<span><\/span> <label> <input type=\"radio\" name=\"question_551_6311\" value=\"1\"><a aria-describedby=\"tt\" href=\"https:\/\/tuhoconline.net\/tu-dien-tieng-nhat\/%e9%a3%9b\" target=\"_blank\">\u98db<\/a>\u3073<a aria-describedby=\"tt\" href=\"https:\/\/tuhoconline.net\/tu-dien-tieng-nhat\/%e8%be%bc\" target=\"_blank\">\u8fbc<\/a>\u3093\u3060 <\/label>","<span><\/span> <label> <input type=\"radio\" name=\"question_551_6311\" value=\"2\"><a aria-describedby=\"tt\" href=\"https:\/\/tuhoconline.net\/tu-dien-tieng-nhat\/%e7%84%a1\" target=\"_blank\">\u7121<\/a>\u8b00 <\/label>","<span><\/span> <label> <input type=\"radio\" name=\"question_551_6311\" value=\"3\"> \u3067\u306a\u304f\u3066\u306a\u3093\u3060\u308d\u3046 <\/label>","<span><\/span> <label> <input type=\"radio\" name=\"question_551_6311\" value=\"4\"> \u3053\u308c\u304c <\/label>"],"answers":[0],"suggestion":null,"solution":null,"sub_quizzes":[]},{"type":"choices","source_title":null,"url":null,"keywords":[],"pre_content":null,"content":"<p><strong><a aria-describedby=\"tt\" target=\"_blank\">\u6b21<\/a>\u306e<a aria-describedby=\"tt\" target=\"_blank\">\u6587<\/a>\u306e\uff3f\u2605\uff3f\u306b\u3082\u3063\u3068\u3082\u3088\u3044\u3082\u306e\u3092\u3001\uff11\u30fb\uff12\u30fb\uff13\u30fb\uff14\u304b\u3089<a aria-describedby=\"tt\" target=\"_blank\">\u4e00<\/a>\u3064\u3048\u3089\u3073\u306a\u3055\u3044<\/strong><\/p>\n<p><a aria-describedby=\"tt\" target=\"_blank\">\u5b50<\/a><a aria-describedby=\"tt\" target=\"_blank\">\u4f9b<\/a>\u3067\u306f\u3000\uff3f\uff3f\u3001\uff3f\u2605\uff3f\u3000\uff3f\uff3f\u3000\uff3f\uff3f\u3000\u306a\u3093\u3066\u3001\u304a\u304b\u3057\u3044\u306d\u3002<\/p>","choices":["<span><\/span> <label> <input type=\"radio\" name=\"question_551_6312\" value=\"1\"> <a aria-describedby=\"tt\" href=\"https:\/\/tuhoconline.net\/tu-dien-tieng-nhat\/%e6%9a%97\" target=\"_blank\">\u6697<\/a>\u3044 <\/label>","<span><\/span> <label> <input type=\"radio\" name=\"question_551_6312\" value=\"2\"> \u6016\u3044 <\/label>","<span><\/span> <label> <input type=\"radio\" name=\"question_551_6312\" value=\"3\"> \u3042\u308b\u3044\u307e\u3044\u3057 <\/label>","<span><\/span> <label> <input type=\"radio\" name=\"question_551_6312\" value=\"4\"> \u3068\u3053\u308d\u304c <\/label>"],"answers":[0],"suggestion":null,"solution":null,"sub_quizzes":[]},{"type":"choices","source_title":null,"url":null,"keywords":[],"pre_content":null,"content":"<p><strong><a aria-describedby=\"tt\" target=\"_blank\">\u6b21<\/a>\u306e<a aria-describedby=\"tt\" target=\"_blank\">\u6587<\/a>\u306e\uff3f\u2605\uff3f\u306b\u3082\u3063\u3068\u3082\u3088\u3044\u3082\u306e\u3092\u3001\uff11\u30fb\uff12\u30fb\uff13\u30fb\uff14\u304b\u3089<a aria-describedby=\"tt\" target=\"_blank\">\u4e00<\/a>\u3064\u3048\u3089\u3073\u306a\u3055\u3044<\/strong><\/p>\n<p>\u3042\u306e\u3000\uff3f\uff3f\u3000\uff3f\uff3f\u3000\uff3f\uff3f\u3000\uff3f\u2605\uff3f\u3000<a aria-describedby=\"tt\" target=\"_blank\">\u771f<\/a>\u5263\u3060\u3002<\/p>","choices":["<span><\/span> <label> <input type=\"radio\" name=\"question_551_6313\" value=\"1\"> \u3067 <\/label>","<span><\/span> <label> <input type=\"radio\" name=\"question_551_6313\" value=\"2\"> \u3042\u304f\u307e\u3067\u3082 <\/label>","<span><\/span> <label> <input type=\"radio\" name=\"question_551_6313\" value=\"3\"><a aria-describedby=\"tt\" href=\"https:\/\/tuhoconline.net\/tu-dien-tieng-nhat\/%e4%ba%ba\" target=\"_blank\">\u4eba<\/a>\u306f <\/label>","<span><\/span> <label> <input type=\"radio\" name=\"question_551_6313\" value=\"4\"><a aria-describedby=\"tt\" href=\"https:\/\/tuhoconline.net\/tu-dien-tieng-nhat\/%e7%a9%8d\" target=\"_blank\">\u7a4d<\/a><a aria-describedby=\"tt\" href=\"https:\/\/tuhoconline.net\/tu-dien-tieng-nhat\/%e6%a5%b5\" target=\"_blank\">\u6975<\/a><a aria-describedby=\"tt\" href=\"https:\/\/tuhoconline.net\/tu-dien-tieng-nhat\/%e7%9a%84\" target=\"_blank\">\u7684<\/a> <\/label>"],"answers":[0],"suggestion":null,"solution":null,"sub_quizzes":[]},{"type":"choices","source_title":null,"url":null,"keywords":[],"pre_content":null,"content":"<p><strong><a aria-describedby=\"tt\" target=\"_blank\">\u6b21<\/a>\u306e<a aria-describedby=\"tt\" target=\"_blank\">\u6587<\/a>\u306e\uff3f\u2605\uff3f\u306b\u3082\u3063\u3068\u3082\u3088\u3044\u3082\u306e\u3092\u3001\uff11\u30fb\uff12\u30fb\uff13\u30fb\uff14\u304b\u3089<a aria-describedby=\"tt\" target=\"_blank\">\u4e00<\/a>\u3064\u3048\u3089\u3073\u306a\u3055\u3044<\/strong><\/p>\n<p>\u3053\u306e<a aria-describedby=\"tt\" target=\"_blank\">\u8fd1<\/a><a aria-describedby=\"tt\" target=\"_blank\">\u6240<\/a>\u3067<a aria-describedby=\"tt\" target=\"_blank\">\u6bba<\/a><a aria-describedby=\"tt\" target=\"_blank\">\u4eba<\/a><a aria-describedby=\"tt\" target=\"_blank\">\u4e8b<\/a><a aria-describedby=\"tt\" target=\"_blank\">\u4ef6<\/a>\u304c\u3000\uff3f\uff3f\u3000\uff3f\u2605\uff3f\u3002\uff3f\uff3f\u3000\uff3f\uff3f\u3002<\/p>","choices":["<span><\/span> <label> <input type=\"radio\" name=\"question_551_6314\" value=\"1\"> \u3089\u3057\u3044 <\/label>","<span><\/span> <label> <input type=\"radio\" name=\"question_551_6314\" value=\"2\"><a aria-describedby=\"tt\" href=\"https:\/\/tuhoconline.net\/tu-dien-tieng-nhat\/%e6%81%90\" target=\"_blank\">\u6050<\/a>\u308d\u3057\u3044 <\/label>","<span><\/span> <label> <input type=\"radio\" name=\"question_551_6314\" value=\"3\"> \u3042\u3063\u305f <\/label>","<span><\/span> <label> <input type=\"radio\" name=\"question_551_6314\" value=\"4\"><a aria-describedby=\"tt\" href=\"https:\/\/tuhoconline.net\/tu-dien-tieng-nhat\/%e9%99%90\" target=\"_blank\">\u9650<\/a>\u308a\u3060 <\/label>"],"answers":[0],"suggestion":null,"solution":null,"sub_quizzes":[]},{"type":"choices","source_title":null,"url":null,"keywords":[],"pre_content":null,"content":"<p><strong><a aria-describedby=\"tt\" target=\"_blank\">\u6b21<\/a>\u306e<a aria-describedby=\"tt\" target=\"_blank\">\u6587<\/a>\u306e\uff3f\u2605\uff3f\u306b\u3082\u3063\u3068\u3082\u3088\u3044\u3082\u306e\u3092\u3001\uff11\u30fb\uff12\u30fb\uff13\u30fb\uff14\u304b\u3089<a aria-describedby=\"tt\" target=\"_blank\">\u4e00<\/a>\u3064\u3048\u3089\u3073\u306a\u3055\u3044<\/strong><\/p>\n<p><a aria-describedby=\"tt\" target=\"_blank\">\u541b<\/a>\u306f\u3000\uff3f\u2605\uff3f\u3000\uff3f\uff3f\u3000\uff3f\uff3f\u3000\uff3f\uff3f\u3000\u3088\u3002<\/p>","choices":["<span><\/span> <label> <input type=\"radio\" name=\"question_551_6315\" value=\"1\"> \u5049<a aria-describedby=\"tt\" href=\"https:\/\/tuhoconline.net\/tu-dien-tieng-nhat\/%e5%a4%a7\" target=\"_blank\">\u5927<\/a>\u306b <\/label>","<span><\/span> <label> <input type=\"radio\" name=\"question_551_6315\" value=\"2\"> \u3042\u308b\u3093\u3060 <\/label>","<span><\/span> <label> <input type=\"radio\" name=\"question_551_6315\" value=\"3\"> \u306a\u308c\u308b <\/label>","<span><\/span> <label> <input type=\"radio\" name=\"question_551_6315\" value=\"4\"><a aria-describedby=\"tt\" href=\"https:\/\/tuhoconline.net\/tu-dien-tieng-nhat\/%e5%8f%af\" target=\"_blank\">\u53ef<\/a><a aria-describedby=\"tt\" href=\"https:\/\/tuhoconline.net\/tu-dien-tieng-nhat\/%e8%83%bd\" target=\"_blank\">\u80fd<\/a><a aria-describedby=\"tt\" href=\"https:\/\/tuhoconline.net\/tu-dien-tieng-nhat\/%e6%80%a7\" target=\"_blank\">\u6027<\/a>\u304c <\/label>"],"answers":[0],"suggestion":null,"solution":null,"sub_quizzes":[]},{"type":"choices","source_title":null,"url":null,"keywords":[],"pre_content":null,"content":"<p><strong><a aria-describedby=\"tt\" target=\"_blank\">\u6b21<\/a>\u306e<a aria-describedby=\"tt\" target=\"_blank\">\u6587<\/a>\u306e\uff3f\u2605\uff3f\u306b\u3082\u3063\u3068\u3082\u3088\u3044\u3082\u306e\u3092\u3001\uff11\u30fb\uff12\u30fb\uff13\u30fb\uff14\u304b\u3089<a aria-describedby=\"tt\" target=\"_blank\">\u4e00<\/a>\u3064\u3048\u3089\u3073\u306a\u3055\u3044<\/strong><\/p>\n<p>\u50d5\u306f\u3053\u308c\u3000\uff3f\uff3f\u3000\uff3f\uff3f\u3000\uff3f\uff3f\u3000\uff3f\u2605\uff3f\u3002<\/p>","choices":["<span><\/span> <label> <input type=\"radio\" name=\"question_551_6316\" value=\"1\"> \u3067\u304d\u306a\u3044 <\/label>","<span><\/span> <label> <input type=\"radio\" name=\"question_551_6316\" value=\"2\"> \u3069\u3046\u306b\u3082 <\/label>","<span><\/span> <label> <input type=\"radio\" name=\"question_551_6316\" value=\"3\"><a aria-describedby=\"tt\" href=\"https:\/\/tuhoconline.net\/tu-dien-tieng-nhat\/%e7%90%86\" target=\"_blank\">\u7406<\/a><a aria-describedby=\"tt\" href=\"https:\/\/tuhoconline.net\/tu-dien-tieng-nhat\/%e8%a7%a3\" target=\"_blank\">\u89e3<\/a> <\/label>","<span><\/span> <label> <input type=\"radio\" name=\"question_551_6316\" value=\"4\"> \u304c <\/label>"],"answers":[0],"suggestion":null,"solution":null,"sub_quizzes":[]},{"type":"choices","source_title":null,"url":null,"keywords":[],"pre_content":null,"content":"<p><strong><a aria-describedby=\"tt\" target=\"_blank\">\u6b21<\/a>\u306e<a aria-describedby=\"tt\" target=\"_blank\">\u6587<\/a>\u306e\uff3f\u2605\uff3f\u306b\u3082\u3063\u3068\u3082\u3088\u3044\u3082\u306e\u3092\u3001\uff11\u30fb\uff12\u30fb\uff13\u30fb\uff14\u304b\u3089<a aria-describedby=\"tt\" target=\"_blank\">\u4e00<\/a>\u3064\u3048\u3089\u3073\u306a\u3055\u3044<\/strong><\/p>\n<p><a aria-describedby=\"tt\" target=\"_blank\">\u9762<\/a><a aria-describedby=\"tt\" target=\"_blank\">\u63a5<\/a>\u306e<a aria-describedby=\"tt\" target=\"_blank\">\u7d50<\/a><a aria-describedby=\"tt\" target=\"_blank\">\u679c<\/a>\u306b\u3064\u3044\u3066\u306f\u3000\uff3f\uff3f\u3000\uff3f\u2605\uff3f\u3000\uff3f\uff3f\u3000\uff3f\uff3f\u3000\u3059\u3079\u304d\u3082\u306e\u3060\u3002<\/p>","choices":["<span><\/span> <label> <input type=\"radio\" name=\"question_551_6317\" value=\"1\"><a aria-describedby=\"tt\" href=\"https:\/\/tuhoconline.net\/tu-dien-tieng-nhat\/%e7%82%b9\" target=\"_blank\">\u70b9<\/a>\u304b\u3089 <\/label>","<span><\/span> <label> <input type=\"radio\" name=\"question_551_6317\" value=\"2\"><a aria-describedby=\"tt\" href=\"https:\/\/tuhoconline.net\/tu-dien-tieng-nhat\/%e6%ba%80\" target=\"_blank\">\u6e80<\/a><a aria-describedby=\"tt\" href=\"https:\/\/tuhoconline.net\/tu-dien-tieng-nhat\/%e8%b6%b3\" target=\"_blank\">\u8db3<\/a> <\/label>","<span><\/span> <label> <input type=\"radio\" name=\"question_551_6317\" value=\"3\"> \u3044\u304b\u306a\u308b <\/label>","<span><\/span> <label> <input type=\"radio\" name=\"question_551_6317\" value=\"4\"><a aria-describedby=\"tt\" href=\"https:\/\/tuhoconline.net\/tu-dien-tieng-nhat\/%e8%80%83\" target=\"_blank\">\u8003<\/a>\u3048\u3066\u3082 <\/label>"],"answers":[0],"suggestion":null,"solution":null,"sub_quizzes":[]},{"type":"choices","source_title":null,"url":null,"keywords":[],"pre_content":null,"content":"<p><strong><a aria-describedby=\"tt\" target=\"_blank\">\u6b21<\/a>\u306e<a aria-describedby=\"tt\" target=\"_blank\">\u6587<\/a>\u306e\uff3f\u2605\uff3f\u306b\u3082\u3063\u3068\u3082\u3088\u3044\u3082\u306e\u3092\u3001\uff11\u30fb\uff12\u30fb\uff13\u30fb\uff14\u304b\u3089<a aria-describedby=\"tt\" target=\"_blank\">\u4e00<\/a>\u3064\u3048\u3089\u3073\u306a\u3055\u3044<\/strong><\/p>\n<p>\uff3f\uff3f\u3000\uff3f\u2605\uff3f\u3000\uff3f\uff3f\u3000\uff3f\uff3f\u3000\u3067\u3059\u3002<\/p>","choices":["<span><\/span> <label> <input type=\"radio\" name=\"question_551_6318\" value=\"1\"> \u30cb\u30e5\u30fc\u30e8\u30fc\u30af <\/label>","<span><\/span> <label> <input type=\"radio\" name=\"question_551_6318\" value=\"2\"> \u51f6<a aria-describedby=\"tt\" href=\"https:\/\/tuhoconline.net\/tu-dien-tieng-nhat\/%e6%82%aa\" target=\"_blank\">\u60aa<\/a><a aria-describedby=\"tt\" href=\"https:\/\/tuhoconline.net\/tu-dien-tieng-nhat\/%e6%bc%a2\" target=\"_blank\">\u6f22<\/a> <\/label>","<span><\/span> <label> <input type=\"radio\" name=\"question_551_6318\" value=\"3\"> <a aria-describedby=\"tt\" href=\"https:\/\/tuhoconline.net\/tu-dien-tieng-nhat\/%e5%bd%bc\" target=\"_blank\">\u5f7c<\/a>\u306f <\/label>","<span><\/span> <label> <input type=\"radio\" name=\"question_551_6318\" value=\"4\"> \u304d\u3063\u3066\u306e <\/label>"],"answers":[0],"suggestion":null,"solution":null,"sub_quizzes":[]},{"type":"choices","source_title":null,"url":null,"keywords":[],"pre_content":null,"content":"<p><strong><a aria-describedby=\"tt\" target=\"_blank\">\u6b21<\/a>\u306e<a aria-describedby=\"tt\" target=\"_blank\">\u6587<\/a>\u306e\uff3f\u2605\uff3f\u306b\u3082\u3063\u3068\u3082\u3088\u3044\u3082\u306e\u3092\u3001\uff11\u30fb\uff12\u30fb\uff13\u30fb\uff14\u304b\u3089<a aria-describedby=\"tt\" target=\"_blank\">\u4e00<\/a>\u3064\u3048\u3089\u3073\u306a\u3055\u3044<\/strong><\/p>\n<p>\uff3f\u2605\uff3f\u3000\uff3f\uff3f\u3000\uff3f\uff3f\u3000\uff3f\uff3f\u3002<\/p>","choices":["<span><\/span> <label> <input type=\"radio\" name=\"question_551_6319\" value=\"1\"> \u305a\u3046\u305a\u3046\u3057\u3044 <\/label>","<span><\/span> <label> <input type=\"radio\" name=\"question_551_6319\" value=\"2\"> \u3042\u308b <\/label>","<span><\/span> <label> <input type=\"radio\" name=\"question_551_6319\" value=\"3\"> \u306b\u3082 <\/label>","<span><\/span> <label> <input type=\"radio\" name=\"question_551_6319\" value=\"4\"> \u307b\u3069\u304c <\/label>"],"answers":[0],"suggestion":null,"solution":null,"sub_quizzes":[]},{"type":"choices","source_title":null,"url":null,"keywords":[],"pre_content":null,"content":"<p><strong><a aria-describedby=\"tt\" target=\"_blank\">\u6b21<\/a>\u306e<a aria-describedby=\"tt\" target=\"_blank\">\u6587<\/a>\u306e\uff3f\u2605\uff3f\u306b\u3082\u3063\u3068\u3082\u3088\u3044\u3082\u306e\u3092\u3001\uff11\u30fb\uff12\u30fb\uff13\u30fb\uff14\u304b\u3089<a aria-describedby=\"tt\" target=\"_blank\">\u4e00<\/a>\u3064\u3048\u3089\u3073\u306a\u3055\u3044<\/strong><\/p>\n<p>\uff3f\u2605\uff3f\u3000\uff3f\uff3f\u3000\uff3f\uff3f\u3000\uff3f\uff3f\u3001\u3064\u3044<a aria-describedby=\"tt\" target=\"_blank\">\u4f59<\/a><a aria-describedby=\"tt\" target=\"_blank\">\u8a08<\/a>\u306a\u3053\u3068\u3092<a aria-describedby=\"tt\" target=\"_blank\">\u8a00<\/a>\u3063\u3066\u3057\u307e\u3063\u305f\u3002<\/p>","choices":["<span><\/span> <label> <input type=\"radio\" name=\"question_551_6320\" value=\"1\"> \u9ed9\u3063\u3066 <\/label>","<span><\/span> <label> <input type=\"radio\" name=\"question_551_6320\" value=\"2\"> \u3044\u3044 <\/label>","<span><\/span> <label> <input type=\"radio\" name=\"question_551_6320\" value=\"3\"> \u3044\u308c\u3070 <\/label>","<span><\/span> <label> <input type=\"radio\" name=\"question_551_6320\" value=\"4\"> \u3082\u306e\u3092 <\/label>"],"answers":[0],"suggestion":null,"solution":null,"sub_quizzes":[]}]}