{"title":"\u0111\u1ec1 luy\u1ec7n t\u1eadp ng\u1eef ph\u00e1p N3 soumatome b\u00e0i 11","url":"https:\/\/tuhoconline.net\/de-luyen-tap-ngu-phap-n3-soumatome-bai-11.html","keywords":["\u0110\u1ec1 thi N3","Luy\u1ec7n thi N3"],"quizzes":[{"type":"choices","source_title":null,"url":null,"keywords":[],"pre_content":null,"content":"<p><strong>_____\u306e<a aria-describedby=\"tt\" target=\"_blank\">\u4e2d<\/a>\u306b\u3001<a aria-describedby=\"tt\" target=\"_blank\">\u4e00<\/a><a aria-describedby=\"tt\" target=\"_blank\">\u756a<\/a><a aria-describedby=\"tt\" target=\"_blank\">\u6b63<\/a>\u3057\u3044<a aria-describedby=\"tt\" target=\"_blank\">\u7b54<\/a>\u3048\u3092<a aria-describedby=\"tt\" target=\"_blank\">\u9078<\/a>\u3093\u3067\u304f\u3060\u3055\u3044<\/strong><strong><\/strong><\/p>\n<p>\u3067\u304d\u308b\u304b\u3067\u304d\u306a\u3044\u304b\u3001\u3068\u306b\u304b\u304f\u3084\u3063\u3066\uff08\u3000\u3000\uff09\u306a\u3055\u3044\u3002<\/p>","choices":["<span><\/span> <label> <input type=\"radio\" name=\"question_620_7067\" value=\"1\"> \u3054\u3089\u3093 <\/label>","<span><\/span> <label> <input type=\"radio\" name=\"question_620_7067\" value=\"2\"> \u307f <\/label>","<span><\/span> <label> <input type=\"radio\" name=\"question_620_7067\" value=\"3\"> \u304f\u308c <\/label>","<span><\/span> <label> <input type=\"radio\" name=\"question_620_7067\" value=\"4\"> \u3057 <\/label>"],"answers":[0],"suggestion":null,"solution":null,"sub_quizzes":[]},{"type":"choices","source_title":null,"url":null,"keywords":[],"pre_content":null,"content":"<p><strong>_____\u306e<a aria-describedby=\"tt\" target=\"_blank\">\u4e2d<\/a>\u306b\u3001<a aria-describedby=\"tt\" target=\"_blank\">\u4e00<\/a><a aria-describedby=\"tt\" target=\"_blank\">\u756a<\/a><a aria-describedby=\"tt\" target=\"_blank\">\u6b63<\/a>\u3057\u3044<a aria-describedby=\"tt\" target=\"_blank\">\u7b54<\/a>\u3048\u3092<a aria-describedby=\"tt\" target=\"_blank\">\u9078<\/a>\u3093\u3067\u304f\u3060\u3055\u3044<\/strong><strong><\/strong><\/p>\n<p><a aria-describedby=\"tt\" target=\"_blank\">\u7530<\/a><a aria-describedby=\"tt\" target=\"_blank\">\u4e2d<\/a>\u3055\u3093\u306b\u3001\u3042\u307e\u308a<a aria-describedby=\"tt\" target=\"_blank\">\u7121<\/a><a aria-describedby=\"tt\" target=\"_blank\">\u7406<\/a>\u3092\uff08\u3000\u3000\uff09<a aria-describedby=\"tt\" target=\"_blank\">\u8a00<\/a>\u3063\u3066\u304f\u3060\u3055\u3044\u3002<\/p>","choices":["<span><\/span> <label> <input type=\"radio\" name=\"question_620_7068\" value=\"1\"> \u3057\u306a\u3044\u3088\u3046\u306b <\/label>","<span><\/span> <label> <input type=\"radio\" name=\"question_620_7068\" value=\"2\"> \u3059\u308b\u306a <\/label>","<span><\/span> <label> <input type=\"radio\" name=\"question_620_7068\" value=\"3\"> \u3059\u308b\u3088\u3046\u306b <\/label>","<span><\/span> <label> <input type=\"radio\" name=\"question_620_7068\" value=\"4\"> \u3057\u308d <\/label>"],"answers":[0],"suggestion":null,"solution":null,"sub_quizzes":[]},{"type":"choices","source_title":null,"url":null,"keywords":[],"pre_content":null,"content":"<p><strong>_____\u306e<a aria-describedby=\"tt\" target=\"_blank\">\u4e2d<\/a>\u306b\u3001<a aria-describedby=\"tt\" target=\"_blank\">\u4e00<\/a><a aria-describedby=\"tt\" target=\"_blank\">\u756a<\/a><a aria-describedby=\"tt\" target=\"_blank\">\u6b63<\/a>\u3057\u3044<a aria-describedby=\"tt\" target=\"_blank\">\u7b54<\/a>\u3048\u3092<a aria-describedby=\"tt\" target=\"_blank\">\u9078<\/a>\u3093\u3067\u304f\u3060\u3055\u3044<\/strong><strong><\/strong><\/p>\n<p><a aria-describedby=\"tt\" target=\"_blank\">\u533b<\/a><a aria-describedby=\"tt\" target=\"_blank\">\u8005<\/a>\u306b\u30bf\u30d0\u30b3\u3092<a aria-describedby=\"tt\" target=\"_blank\">\u5438<\/a>\u3044\uff08\u3000\u3000\u3000\uff09\u3068<a aria-describedby=\"tt\" target=\"_blank\">\u6ce8<\/a><a aria-describedby=\"tt\" target=\"_blank\">\u610f<\/a>\u3055\u308c\u307e\u3057\u305f\u3002<\/p>","choices":["<span><\/span> <label> <input type=\"radio\" name=\"question_620_7069\" value=\"1\"> \u3059\u304e\u308b\u306a <\/label>","<span><\/span> <label> <input type=\"radio\" name=\"question_620_7069\" value=\"2\"> \u3059\u304e\u308d <\/label>","<span><\/span> <label> <input type=\"radio\" name=\"question_620_7069\" value=\"3\"> \u3059\u304e\u308b <\/label>","<span><\/span> <label> <input type=\"radio\" name=\"question_620_7069\" value=\"4\"> \u3059\u304e\u306a\u3044 <\/label>"],"answers":[0],"suggestion":null,"solution":null,"sub_quizzes":[]},{"type":"choices","source_title":null,"url":null,"keywords":[],"pre_content":null,"content":"<p><strong>_____\u306e<a aria-describedby=\"tt\" target=\"_blank\">\u4e2d<\/a>\u306b\u3001<a aria-describedby=\"tt\" target=\"_blank\">\u4e00<\/a><a aria-describedby=\"tt\" target=\"_blank\">\u756a<\/a><a aria-describedby=\"tt\" target=\"_blank\">\u6b63<\/a>\u3057\u3044<a aria-describedby=\"tt\" target=\"_blank\">\u7b54<\/a>\u3048\u3092<a aria-describedby=\"tt\" target=\"_blank\">\u9078<\/a>\u3093\u3067\u304f\u3060\u3055\u3044<\/strong><strong><\/strong><\/p>\n<p><a aria-describedby=\"tt\" target=\"_blank\">\u660e<\/a><a aria-describedby=\"tt\" target=\"_blank\">\u65e5<\/a>\u306f\uff18<a aria-describedby=\"tt\" target=\"_blank\">\u6642<\/a>\u307e\u3067\u306b<a aria-describedby=\"tt\" target=\"_blank\">\u4f1a<\/a><a aria-describedby=\"tt\" target=\"_blank\">\u793e<\/a>\u306b\uff08\u3000\u3000\u3000\uff09\u3068\u3044\u308f\u308c\u307e\u3057\u305f<\/p>","choices":["<span><\/span> <label> <input type=\"radio\" name=\"question_620_7070\" value=\"1\"> \u304f\u308d <\/label>","<span><\/span> <label> <input type=\"radio\" name=\"question_620_7070\" value=\"2\"> \u3053\u3044 <\/label>","<span><\/span> <label> <input type=\"radio\" name=\"question_620_7070\" value=\"3\"> \u304f\u308b <\/label>","<span><\/span> <label> <input type=\"radio\" name=\"question_620_7070\" value=\"4\"> \u304d\u3066 <\/label>"],"answers":[0],"suggestion":null,"solution":null,"sub_quizzes":[]},{"type":"choices","source_title":null,"url":null,"keywords":[],"pre_content":null,"content":"<p><strong>_____\u306e<a aria-describedby=\"tt\" target=\"_blank\">\u4e2d<\/a>\u306b\u3001<a aria-describedby=\"tt\" target=\"_blank\">\u4e00<\/a><a aria-describedby=\"tt\" target=\"_blank\">\u756a<\/a><a aria-describedby=\"tt\" target=\"_blank\">\u6b63<\/a>\u3057\u3044<a aria-describedby=\"tt\" target=\"_blank\">\u7b54<\/a>\u3048\u3092<a aria-describedby=\"tt\" target=\"_blank\">\u9078<\/a>\u3093\u3067\u304f\u3060\u3055\u3044<\/strong><strong><\/strong><\/p>\n<p>\u3053\u306e<a aria-describedby=\"tt\" target=\"_blank\">\u8cc7<\/a><a aria-describedby=\"tt\" target=\"_blank\">\u6599<\/a>\u3092\uff15\uff10<a aria-describedby=\"tt\" target=\"_blank\">\u90e8<\/a>\u30b3\u30d4\u30fc\u3059\u308b\uff08\u3000\u3000\uff09<a aria-describedby=\"tt\" target=\"_blank\">\u983c<\/a>\u307e\u308c\u307e\u3057\u305f\u3002<\/p>","choices":["<span><\/span> <label> <input type=\"radio\" name=\"question_620_7071\" value=\"1\"> \u304f\u308c\u3068 <\/label>","<span><\/span> <label> <input type=\"radio\" name=\"question_620_7071\" value=\"2\"> \u3088\u3046\u306b <\/label>","<span><\/span> <label> <input type=\"radio\" name=\"question_620_7071\" value=\"3\"> \u3057\u308d <\/label>","<span><\/span> <label> <input type=\"radio\" name=\"question_620_7071\" value=\"4\"> \u3068 <\/label>"],"answers":[0],"suggestion":null,"solution":null,"sub_quizzes":[]},{"type":"choices","source_title":null,"url":null,"keywords":[],"pre_content":null,"content":"<p><strong><a aria-describedby=\"tt\" target=\"_blank\">\u6b21<\/a>\u306e<a aria-describedby=\"tt\" target=\"_blank\">\u6587<\/a>\u306e\uff3f\u2605\uff3f\u306b\u3082\u3063\u3068\u3082\u3088\u3044\u3082\u306e\u3092\u3001\uff11\u30fb\uff12\u30fb\uff13\u30fb\uff14\u304b\u3089<a aria-describedby=\"tt\" target=\"_blank\">\u4e00<\/a>\u3064\u3048\u3089\u3073\u306a\u3055\u3044<\/strong><strong><\/strong><\/p>\n<p>\u3053\u306e<a aria-describedby=\"tt\" target=\"_blank\">\u8a00<\/a><a aria-describedby=\"tt\" target=\"_blank\">\u8449<\/a>\u306f\u8ab0\u306b\u3082 \uff3f\uff3f\uff3f \uff3f\u2605\uff3f \uff3f\uff3f\uff3f \uff3f\uff3f\uff3f\u3093\u3067\u3059\u3002<\/p>","choices":["<span><\/span> <label> <input type=\"radio\" name=\"question_620_7072\" value=\"1\"> \u304f\u308c\u3068 <\/label>","<span><\/span> <label> <input type=\"radio\" name=\"question_620_7072\" value=\"2\"><a aria-describedby=\"tt\" href=\"https:\/\/tuhoconline.net\/tu-dien-tieng-nhat\/%e8%a8%80\" target=\"_blank\">\u8a00<\/a>\u308f\u308c\u305f <\/label>","<span><\/span> <label> <input type=\"radio\" name=\"question_620_7072\" value=\"3\"> \u3068 <\/label>","<span><\/span> <label> <input type=\"radio\" name=\"question_620_7072\" value=\"4\"><a aria-describedby=\"tt\" href=\"https:\/\/tuhoconline.net\/tu-dien-tieng-nhat\/%e8%a8%80\" target=\"_blank\">\u8a00<\/a>\u308f\u306a\u3044\u3067 <\/label>"],"answers":[0],"suggestion":null,"solution":null,"sub_quizzes":[]},{"type":"choices","source_title":null,"url":null,"keywords":[],"pre_content":null,"content":"<p><strong><a aria-describedby=\"tt\" target=\"_blank\">\u6b21<\/a>\u306e<a aria-describedby=\"tt\" target=\"_blank\">\u6587<\/a>\u306e\uff3f\u2605\uff3f\u306b\u3082\u3063\u3068\u3082\u3088\u3044\u3082\u306e\u3092\u3001\uff11\u30fb\uff12\u30fb\uff13\u30fb\uff14\u304b\u3089<a aria-describedby=\"tt\" target=\"_blank\">\u4e00<\/a>\u3064\u3048\u3089\u3073\u306a\u3055\u3044<\/strong><strong><\/strong><\/p>\n<p>\u300c\u3042\u308c\u306f<a aria-describedby=\"tt\" target=\"_blank\">\u5ea6<\/a><a aria-describedby=\"tt\" target=\"_blank\">\u8a00<\/a>\u3046<a aria-describedby=\"tt\" target=\"_blank\">\u610f<\/a><a aria-describedby=\"tt\" target=\"_blank\">\u5473<\/a>\u3067\u3059\u304b\u300d\u300c\u304a<a aria-describedby=\"tt\" target=\"_blank\">\u9152<\/a>\u3092 \uff3f\u2605\uff3f \uff3f\uff3f\uff3f \uff3f\uff3f\uff3f \uff3f\uff3f\uff3f\u3068\u3044\u3046<a aria-describedby=\"tt\" target=\"_blank\">\u610f<\/a><a aria-describedby=\"tt\" target=\"_blank\">\u5473<\/a>\u3067\u3059\u300d<\/p>","choices":["<span><\/span> <label> <input type=\"radio\" name=\"question_620_7073\" value=\"1\"> \u304a<a aria-describedby=\"tt\" href=\"https:\/\/tuhoconline.net\/tu-dien-tieng-nhat\/%e9%85%92\" target=\"_blank\">\u9152<\/a>\u3092<a aria-describedby=\"tt\" href=\"https:\/\/tuhoconline.net\/tu-dien-tieng-nhat\/%e9%a3%b2\" target=\"_blank\">\u98f2<\/a>\u3080\u306a <\/label>","<span><\/span> <label> <input type=\"radio\" name=\"question_620_7073\" value=\"2\"> <a aria-describedby=\"tt\" href=\"https:\/\/tuhoconline.net\/tu-dien-tieng-nhat\/%e9%81%8b\" target=\"_blank\">\u904b<\/a><a aria-describedby=\"tt\" href=\"https:\/\/tuhoconline.net\/tu-dien-tieng-nhat\/%e8%bb%a2\" target=\"_blank\">\u8ee2<\/a>\u3059\u308b\u306a\u3089 <\/label>","<span><\/span> <label> <input type=\"radio\" name=\"question_620_7073\" value=\"3\"><a aria-describedby=\"tt\" href=\"https:\/\/tuhoconline.net\/tu-dien-tieng-nhat\/%e9%a3%b2\" target=\"_blank\">\u98f2<\/a>\u3093\u3060\u3089 <\/label>","<span><\/span> <label> <input type=\"radio\" name=\"question_620_7073\" value=\"4\"> <a aria-describedby=\"tt\" href=\"https:\/\/tuhoconline.net\/tu-dien-tieng-nhat\/%e9%81%8b\" target=\"_blank\">\u904b<\/a><a aria-describedby=\"tt\" href=\"https:\/\/tuhoconline.net\/tu-dien-tieng-nhat\/%e8%bb%a2\" target=\"_blank\">\u8ee2<\/a>\u3059\u308b\u306a <\/label>"],"answers":[0],"suggestion":null,"solution":null,"sub_quizzes":[]},{"type":"choices","source_title":null,"url":null,"keywords":[],"pre_content":null,"content":"<p><strong><a aria-describedby=\"tt\" target=\"_blank\">\u6b21<\/a>\u306e<a aria-describedby=\"tt\" target=\"_blank\">\u6587<\/a>\u306e\uff3f\u2605\uff3f\u306b\u3082\u3063\u3068\u3082\u3088\u3044\u3082\u306e\u3092\u3001\uff11\u30fb\uff12\u30fb\uff13\u30fb\uff14\u304b\u3089<a aria-describedby=\"tt\" target=\"_blank\">\u4e00<\/a>\u3064\u3048\u3089\u3073\u306a\u3055\u3044<\/strong><strong><\/strong><\/p>\n<p><a aria-describedby=\"tt\" target=\"_blank\">\u7530<\/a><a aria-describedby=\"tt\" target=\"_blank\">\u4e2d<\/a>\u3055\u3093\u306b\u3001<a aria-describedby=\"tt\" target=\"_blank\">\u79c1<\/a>\u306e \uff3f\uff3f\uff3f \uff3f\uff3f\uff3f \uff3f\u2605\uff3f \uff3f\uff3f\uff3f\u304f\u3060\u3055\u3044\u3002<\/p>","choices":["<span><\/span> <label> <input type=\"radio\" name=\"question_620_7074\" value=\"1\"> \u3088\u3046\uff08\u306b\uff09 <\/label>","<span><\/span> <label> <input type=\"radio\" name=\"question_620_7074\" value=\"2\"><a aria-describedby=\"tt\" href=\"https:\/\/tuhoconline.net\/tu-dien-tieng-nhat\/%e9%83%a8\" target=\"_blank\">\u90e8<\/a><a aria-describedby=\"tt\" href=\"https:\/\/tuhoconline.net\/tu-dien-tieng-nhat\/%e5%b1%8b\" target=\"_blank\">\u5c4b<\/a>\u306b <\/label>","<span><\/span> <label> <input type=\"radio\" name=\"question_620_7074\" value=\"3\"><a aria-describedby=\"tt\" href=\"https:\/\/tuhoconline.net\/tu-dien-tieng-nhat\/%e8%a8%80\" target=\"_blank\">\u8a00<\/a>\u3063\u3066 <\/label>","<span><\/span> <label> <input type=\"radio\" name=\"question_620_7074\" value=\"4\"><a aria-describedby=\"tt\" href=\"https:\/\/tuhoconline.net\/tu-dien-tieng-nhat\/%e6%9d%a5\" target=\"_blank\">\u6765<\/a>\u308b <\/label>"],"answers":[0],"suggestion":null,"solution":null,"sub_quizzes":[]},{"type":"choices","source_title":null,"url":null,"keywords":[],"pre_content":null,"content":"<p><strong><a aria-describedby=\"tt\" target=\"_blank\">\u6b21<\/a>\u306e<a aria-describedby=\"tt\" target=\"_blank\">\u6587<\/a>\u306e\uff3f\u2605\uff3f\u306b\u3082\u3063\u3068\u3082\u3088\u3044\u3082\u306e\u3092\u3001\uff11\u30fb\uff12\u30fb\uff13\u30fb\uff14\u304b\u3089<a aria-describedby=\"tt\" target=\"_blank\">\u4e00<\/a>\u3064\u3048\u3089\u3073\u306a\u3055\u3044<\/strong><strong><\/strong><\/p>\n<p><a aria-describedby=\"tt\" target=\"_blank\">\u7236<\/a>\u306b\u3001\u3082\u3063\u3068 \uff3f\uff3f\uff3f \uff3f\u2605\uff3f \uff3f\uff3f\uff3f \uff3f\uff3f\uff3f \u3002<\/p>","choices":["<span><\/span> <label> <input type=\"radio\" name=\"question_620_7075\" value=\"1\"> \u3068 <\/label>","<span><\/span> <label> <input type=\"radio\" name=\"question_620_7075\" value=\"2\"><a aria-describedby=\"tt\" href=\"https:\/\/tuhoconline.net\/tu-dien-tieng-nhat\/%e6%97%a9\" target=\"_blank\">\u65e9<\/a>\u304f <\/label>","<span><\/span> <label> <input type=\"radio\" name=\"question_620_7075\" value=\"3\"><a aria-describedby=\"tt\" href=\"https:\/\/tuhoconline.net\/tu-dien-tieng-nhat\/%e6%b3%a8\" target=\"_blank\">\u6ce8<\/a><a aria-describedby=\"tt\" href=\"https:\/\/tuhoconline.net\/tu-dien-tieng-nhat\/%e6%84%8f\" target=\"_blank\">\u610f<\/a>\u3055\u308c\u305f <\/label>","<span><\/span> <label> <input type=\"radio\" name=\"question_620_7075\" value=\"4\"><a aria-describedby=\"tt\" href=\"https:\/\/tuhoconline.net\/tu-dien-tieng-nhat\/%e5%b8%b0\" target=\"_blank\">\u5e30<\/a>\u308c <\/label>"],"answers":[0],"suggestion":null,"solution":null,"sub_quizzes":[]},{"type":"choices","source_title":null,"url":null,"keywords":[],"pre_content":null,"content":"<p><strong><a aria-describedby=\"tt\" target=\"_blank\">\u6b21<\/a>\u306e<a aria-describedby=\"tt\" target=\"_blank\">\u6587<\/a>\u306e\uff3f\u2605\uff3f\u306b\u3082\u3063\u3068\u3082\u3088\u3044\u3082\u306e\u3092\u3001\uff11\u30fb\uff12\u30fb\uff13\u30fb\uff14\u304b\u3089<a aria-describedby=\"tt\" target=\"_blank\">\u4e00<\/a>\u3064\u3048\u3089\u3073\u306a\u3055\u3044<\/strong><strong><\/strong><\/p>\n<p><a aria-describedby=\"tt\" target=\"_blank\">\u5927<\/a><a aria-describedby=\"tt\" target=\"_blank\">\u5bb6<\/a>\u306b\u3001\u7384<a aria-describedby=\"tt\" target=\"_blank\">\u95a2<\/a>\u306e<a aria-describedby=\"tt\" target=\"_blank\">\u524d<\/a>\u306b \uff3f\uff3f\uff3f \uff3f\uff3f\uff3f \uff3f\u2605\uff3f \uff3f\uff3f\uff3f\u3002<\/p>","choices":["<span><\/span> <label> <input type=\"radio\" name=\"question_620_7076\" value=\"1\"> \u304f\u308c\u3068 <\/label>","<span><\/span> <label> <input type=\"radio\" name=\"question_620_7076\" value=\"2\"><a aria-describedby=\"tt\" href=\"https:\/\/tuhoconline.net\/tu-dien-tieng-nhat\/%e8%87%aa\" target=\"_blank\">\u81ea<\/a><a aria-describedby=\"tt\" href=\"https:\/\/tuhoconline.net\/tu-dien-tieng-nhat\/%e8%bb%a2\" target=\"_blank\">\u8ee2<\/a><a aria-describedby=\"tt\" href=\"https:\/\/tuhoconline.net\/tu-dien-tieng-nhat\/%e8%bb%8a\" target=\"_blank\">\u8eca<\/a>\u3092 <\/label>","<span><\/span> <label> <input type=\"radio\" name=\"question_620_7076\" value=\"3\"> \u304a\u304b\u306a\u3044\u3067 <\/label>","<span><\/span> <label> <input type=\"radio\" name=\"question_620_7076\" value=\"4\"><a aria-describedby=\"tt\" href=\"https:\/\/tuhoconline.net\/tu-dien-tieng-nhat\/%e8%a8%80\" target=\"_blank\">\u8a00<\/a>\u308f\u308c\u305f <\/label>"],"answers":[0],"suggestion":null,"solution":null,"sub_quizzes":[]}]}