{"title":"Luy\u1ec7n nghe ti\u1ebfng Nh\u1eadt N4 online","url":"https:\/\/tuhoconline.net\/luyen-nghe-tieng-nhat-n4-online.html","keywords":["\u0110\u1ec1 thi N4"],"quizzes":[{"type":"choices","source_title":null,"url":null,"keywords":[],"pre_content":null,"content":"<p>[youtube id=\u201dJSujlgw12Rs\u201d]<\/p>","choices":["<span><\/span> <label> <input type=\"radio\" name=\"question_65_1248\" value=\"1\"> 1 <\/label>","<span><\/span> <label> <input type=\"radio\" name=\"question_65_1248\" value=\"2\"> 2 <\/label>","<span><\/span> <label> <input type=\"radio\" name=\"question_65_1248\" value=\"3\"> 3 <\/label>","<span><\/span> <label> <input type=\"radio\" name=\"question_65_1248\" value=\"4\"> 4 <\/label>"],"answers":[0],"suggestion":null,"solution":null,"sub_quizzes":[]},{"type":"choices","source_title":null,"url":null,"keywords":[],"pre_content":null,"content":"<p>[youtube id=\u201doGxkkkC9vs8\u2033]<\/p>","choices":["<span><\/span> <label> <input type=\"radio\" name=\"question_65_1249\" value=\"1\"> 1 <\/label>","<span><\/span> <label> <input type=\"radio\" name=\"question_65_1249\" value=\"2\"> 2 <\/label>","<span><\/span> <label> <input type=\"radio\" name=\"question_65_1249\" value=\"3\"> 3 <\/label>","<span><\/span> <label> <input type=\"radio\" name=\"question_65_1249\" value=\"4\"> 4 <\/label>"],"answers":[0],"suggestion":null,"solution":null,"sub_quizzes":[]},{"type":"choices","source_title":null,"url":null,"keywords":[],"pre_content":null,"content":"<p>[youtube id=\u201dILgWGNYn8a4\u2033]<\/p>","choices":["<span><\/span> <label> <input type=\"radio\" name=\"question_65_1250\" value=\"1\"> 1 <\/label>","<span><\/span> <label> <input type=\"radio\" name=\"question_65_1250\" value=\"2\"> 2 <\/label>","<span><\/span> <label> <input type=\"radio\" name=\"question_65_1250\" value=\"3\"> 3 <\/label>","<span><\/span> <label> <input type=\"radio\" name=\"question_65_1250\" value=\"4\"> 4 <\/label>"],"answers":[0],"suggestion":null,"solution":null,"sub_quizzes":[]},{"type":"choices","source_title":null,"url":null,"keywords":[],"pre_content":null,"content":"<p>[youtube id=\u201dLq4SwBMdWgs\u201d]<\/p>","choices":["<span><\/span> <label> <input type=\"radio\" name=\"question_65_1251\" value=\"1\"> 1 <\/label>","<span><\/span> <label> <input type=\"radio\" name=\"question_65_1251\" value=\"2\"> 2 <\/label>","<span><\/span> <label> <input type=\"radio\" name=\"question_65_1251\" value=\"3\"> 3 <\/label>","<span><\/span> <label> <input type=\"radio\" name=\"question_65_1251\" value=\"4\"> 4 <\/label>"],"answers":[0],"suggestion":null,"solution":null,"sub_quizzes":[]},{"type":"choices","source_title":null,"url":null,"keywords":[],"pre_content":null,"content":"<p>[youtube id=\u201dl0gjx5NAya4\u2033]<\/p>","choices":["<span><\/span> <label> <input type=\"radio\" name=\"question_65_1252\" value=\"1\"> 1 <\/label>","<span><\/span> <label> <input type=\"radio\" name=\"question_65_1252\" value=\"2\"> 2 <\/label>","<span><\/span> <label> <input type=\"radio\" name=\"question_65_1252\" value=\"3\"> 3 <\/label>","<span><\/span> <label> <input type=\"radio\" name=\"question_65_1252\" value=\"4\"> 4 <\/label>"],"answers":[0],"suggestion":null,"solution":null,"sub_quizzes":[]},{"type":"choices","source_title":null,"url":null,"keywords":[],"pre_content":null,"content":"<p>[youtube id=\u201dEbf8BEoyq-U\u201d]<\/p>","choices":["<span><\/span> <label> <input type=\"radio\" name=\"question_65_1253\" value=\"1\"> 1 <\/label>","<span><\/span> <label> <input type=\"radio\" name=\"question_65_1253\" value=\"2\"> 2 <\/label>","<span><\/span> <label> <input type=\"radio\" name=\"question_65_1253\" value=\"3\"> 3 <\/label>","<span><\/span> <label> <input type=\"radio\" name=\"question_65_1253\" value=\"4\"> 4 <\/label>"],"answers":[0],"suggestion":null,"solution":null,"sub_quizzes":[]},{"type":"choices","source_title":null,"url":null,"keywords":[],"pre_content":null,"content":"<p>[youtube id=\u201dmtZr9HdgH8k\u201d]<\/p>","choices":["<span><\/span> <label> <input type=\"radio\" name=\"question_65_1254\" value=\"1\"> 1 <\/label>","<span><\/span> <label> <input type=\"radio\" name=\"question_65_1254\" value=\"2\"> 2 <\/label>","<span><\/span> <label> <input type=\"radio\" name=\"question_65_1254\" value=\"3\"> 3 <\/label>","<span><\/span> <label> <input type=\"radio\" name=\"question_65_1254\" value=\"4\"> 4 <\/label>"],"answers":[0],"suggestion":null,"solution":null,"sub_quizzes":[]},{"type":"choices","source_title":null,"url":null,"keywords":[],"pre_content":null,"content":"<p>[youtube id=\u201dxm8Q5yxCoe0\u2033]<\/p>","choices":["<span><\/span> <label> <input type=\"radio\" name=\"question_65_1255\" value=\"1\"> 1 <\/label>","<span><\/span> <label> <input type=\"radio\" name=\"question_65_1255\" value=\"2\"> 2 <\/label>","<span><\/span> <label> <input type=\"radio\" name=\"question_65_1255\" value=\"3\"> 3 <\/label>","<span><\/span> <label> <input type=\"radio\" name=\"question_65_1255\" value=\"4\"> 4 <\/label>"],"answers":[0],"suggestion":null,"solution":null,"sub_quizzes":[]},{"type":"choices","source_title":null,"url":null,"keywords":[],"pre_content":null,"content":"<p>[youtube id=\u201dxpI6C-pBQGY\u201d]<\/p>","choices":["<span><\/span> <label> <input type=\"radio\" name=\"question_65_1256\" value=\"1\"> 1 <\/label>","<span><\/span> <label> <input type=\"radio\" name=\"question_65_1256\" value=\"2\"> 2 <\/label>","<span><\/span> <label> <input type=\"radio\" name=\"question_65_1256\" value=\"3\"> 3 <\/label>","<span><\/span> <label> <input type=\"radio\" name=\"question_65_1256\" value=\"4\"> 4 <\/label>"],"answers":[0],"suggestion":null,"solution":null,"sub_quizzes":[]},{"type":"choices","source_title":null,"url":null,"keywords":[],"pre_content":null,"content":"<p>[youtube id=\u201dA_Y4SBlzvJo\u201d]<\/p>","choices":["<span><\/span> <label> <input type=\"radio\" name=\"question_65_1257\" value=\"1\"> 1 <\/label>","<span><\/span> <label> <input type=\"radio\" name=\"question_65_1257\" value=\"2\"> 2 <\/label>","<span><\/span> <label> <input type=\"radio\" name=\"question_65_1257\" value=\"3\"> 3 <\/label>","<span><\/span> <label> <input type=\"radio\" name=\"question_65_1257\" value=\"4\"> 4 <\/label>"],"answers":[0],"suggestion":null,"solution":null,"sub_quizzes":[]}]}